{
  "updated": "2026-02-17T13:30:27.172706+09:00",
  "total_completed": 29,
  "total_open": 18,
  "today_entries": 47,
  "param_summary": {
    "conservative": {
      "params": {
        "act": 8.0,
        "trail": 3.0,
        "sl": -15.0
      },
      "trades": 29,
      "win_rate": 44.8,
      "avg_pnl_pct": -1.84,
      "total_pnl_pct": -53.47,
      "total_pnl_usd": -10.69,
      "best_trade": 56.78,
      "worst_trade": -39.83,
      "reasons": {
        "SL": 13,
        "TRAIL": 16,
        "TIMEOUT": 0
      }
    },
    "current": {
      "params": {
        "act": 5.0,
        "trail": 3.0,
        "sl": -15.0
      },
      "trades": 29,
      "win_rate": 48.3,
      "avg_pnl_pct": -1.09,
      "total_pnl_pct": -31.73,
      "total_pnl_usd": -6.35,
      "best_trade": 56.78,
      "worst_trade": -39.83,
      "reasons": {
        "SL": 11,
        "TRAIL": 18,
        "TIMEOUT": 0
      }
    },
    "moderate": {
      "params": {
        "act": 3.0,
        "trail": 2.0,
        "sl": -15.0
      },
      "trades": 29,
      "win_rate": 44.8,
      "avg_pnl_pct": -1.08,
      "total_pnl_pct": -31.22,
      "total_pnl_usd": -6.24,
      "best_trade": 55.42,
      "worst_trade": -39.83,
      "reasons": {
        "SL": 8,
        "TRAIL": 21,
        "TIMEOUT": 0
      }
    },
    "tight": {
      "params": {
        "act": 3.0,
        "trail": 1.5,
        "sl": -15.0
      },
      "trades": 29,
      "win_rate": 44.8,
      "avg_pnl_pct": -2.21,
      "total_pnl_pct": -64.02,
      "total_pnl_usd": -12.8,
      "best_trade": 55.42,
      "worst_trade": -39.83,
      "reasons": {
        "SL": 8,
        "TRAIL": 21,
        "TIMEOUT": 0
      }
    },
    "aggressive": {
      "params": {
        "act": 2.0,
        "trail": 1.0,
        "sl": -15.0
      },
      "trades": 29,
      "win_rate": 44.8,
      "avg_pnl_pct": -2.03,
      "total_pnl_pct": -58.96,
      "total_pnl_usd": -11.79,
      "best_trade": 55.42,
      "worst_trade": -39.83,
      "reasons": {
        "SL": 7,
        "TRAIL": 22,
        "TIMEOUT": 0
      }
    },
    "wide_trail": {
      "params": {
        "act": 5.0,
        "trail": 2.0,
        "sl": -15.0
      },
      "trades": 29,
      "win_rate": 48.3,
      "avg_pnl_pct": -2.64,
      "total_pnl_pct": -76.46,
      "total_pnl_usd": -15.29,
      "best_trade": 55.42,
      "worst_trade": -39.83,
      "reasons": {
        "SL": 11,
        "TRAIL": 18,
        "TIMEOUT": 0
      }
    },
    "low_act": {
      "params": {
        "act": 2.5,
        "trail": 1.5,
        "sl": -15.0
      },
      "trades": 29,
      "win_rate": 44.8,
      "avg_pnl_pct": -2.21,
      "total_pnl_pct": -64.02,
      "total_pnl_usd": -12.8,
      "best_trade": 55.42,
      "worst_trade": -39.83,
      "reasons": {
        "SL": 8,
        "TRAIL": 21,
        "TIMEOUT": 0
      }
    },
    "micro": {
      "params": {
        "act": 1.5,
        "trail": 0.8,
        "sl": -15.0
      },
      "trades": 29,
      "win_rate": 44.8,
      "avg_pnl_pct": -2.02,
      "total_pnl_pct": -58.47,
      "total_pnl_usd": -11.69,
      "best_trade": 55.42,
      "worst_trade": -39.83,
      "reasons": {
        "SL": 7,
        "TRAIL": 22,
        "TIMEOUT": 0
      }
    }
  },
  "open_positions": [
    {
      "symbol": "DONALDMINAJ",
      "entry_time": "2026-02-17T13:04:55.989110+09:00",
      "entry_price": 0.003883,
      "current_pnl_pct": 13.39,
      "peak_pnl_pct": 13.39170744269893,
      "price_points": 126,
      "active_params": [
        "conservative",
        "current"
      ],
      "score": 70.62769538863927,
      "grade": "A"
    },
    {
      "symbol": "Orangutan",
      "entry_time": "2026-02-17T13:22:55.012906+09:00",
      "entry_price": 8.312e-05,
      "current_pnl_pct": 1.91,
      "peak_pnl_pct": 1.9128970163618808,
      "price_points": 35,
      "active_params": [
        "conservative",
        "current",
        "moderate",
        "tight",
        "aggressive",
        "wide_trail",
        "low_act",
        "micro"
      ],
      "score": 47.20719732571337,
      "grade": "C"
    },
    {
      "symbol": "Buddy",
      "entry_time": "2026-02-17T13:26:59.531271+09:00",
      "entry_price": 2.275e-05,
      "current_pnl_pct": -5.58,
      "peak_pnl_pct": 0.0,
      "price_points": 19,
      "active_params": [
        "conservative",
        "current",
        "moderate",
        "tight",
        "aggressive",
        "wide_trail",
        "low_act",
        "micro"
      ],
      "score": 66.45306202272995,
      "grade": "A"
    },
    {
      "symbol": "TRUMPIUS",
      "entry_time": "2026-02-17T13:26:59.532301+09:00",
      "entry_price": 0.01047,
      "current_pnl_pct": 1.91,
      "peak_pnl_pct": 1.9102196752626588,
      "price_points": 19,
      "active_params": [
        "conservative",
        "current",
        "moderate",
        "tight",
        "aggressive",
        "wide_trail",
        "low_act",
        "micro"
      ],
      "score": 53.79145603645034,
      "grade": "B"
    },
    {
      "symbol": "SAID",
      "entry_time": "2026-02-17T13:26:59.532774+09:00",
      "entry_price": 0.0003746,
      "current_pnl_pct": 14.71,
      "peak_pnl_pct": 14.709022957821682,
      "price_points": 19,
      "active_params": [
        "conservative",
        "current",
        "moderate",
        "wide_trail"
      ],
      "score": 42.225483793235924,
      "grade": "C"
    },
    {
      "symbol": "PEPE",
      "entry_time": "2026-02-17T13:26:59.534114+09:00",
      "entry_price": 1.009e-05,
      "current_pnl_pct": 0.0,
      "peak_pnl_pct": 0.0,
      "price_points": 19,
      "active_params": [
        "conservative",
        "current",
        "moderate",
        "tight",
        "aggressive",
        "wide_trail",
        "low_act",
        "micro"
      ],
      "score": 29.0,
      "grade": "D"
    },
    {
      "symbol": "PEPE",
      "entry_time": "2026-02-17T13:26:59.534638+09:00",
      "entry_price": 1.247e-05,
      "current_pnl_pct": 0.0,
      "peak_pnl_pct": 0.0,
      "price_points": 19,
      "active_params": [
        "conservative",
        "current",
        "moderate",
        "tight",
        "aggressive",
        "wide_trail",
        "low_act",
        "micro"
      ],
      "score": 29.0,
      "grade": "D"
    },
    {
      "symbol": "PEPE",
      "entry_time": "2026-02-17T13:26:59.535560+09:00",
      "entry_price": 0.001007,
      "current_pnl_pct": 0.0,
      "peak_pnl_pct": 0.0,
      "price_points": 19,
      "active_params": [
        "conservative",
        "current",
        "moderate",
        "tight",
        "aggressive",
        "wide_trail",
        "low_act",
        "micro"
      ],
      "score": 29.0,
      "grade": "D"
    },
    {
      "symbol": "PEPE",
      "entry_time": "2026-02-17T13:26:59.536165+09:00",
      "entry_price": 6.004e-06,
      "current_pnl_pct": 0.0,
      "peak_pnl_pct": 0.0,
      "price_points": 19,
      "active_params": [
        "conservative",
        "current",
        "moderate",
        "tight",
        "aggressive",
        "wide_trail",
        "low_act",
        "micro"
      ],
      "score": 26.860221749157432,
      "grade": "D"
    },
    {
      "symbol": "Pepe",
      "entry_time": "2026-02-17T13:26:59.536638+09:00",
      "entry_price": 0.0002794,
      "current_pnl_pct": 0.0,
      "peak_pnl_pct": 0.0,
      "price_points": 19,
      "active_params": [
        "conservative",
        "current",
        "moderate",
        "tight",
        "aggressive",
        "wide_trail",
        "low_act",
        "micro"
      ],
      "score": 24.855046223030158,
      "grade": "D"
    },
    {
      "symbol": "PEPE",
      "entry_time": "2026-02-17T13:26:59.537065+09:00",
      "entry_price": 0.0001974,
      "current_pnl_pct": 0.0,
      "peak_pnl_pct": 0.0,
      "price_points": 19,
      "active_params": [
        "conservative",
        "current",
        "moderate",
        "tight",
        "aggressive",
        "wide_trail",
        "low_act",
        "micro"
      ],
      "score": 24.09527284470598,
      "grade": "D"
    },
    {
      "symbol": "PEPE",
      "entry_time": "2026-02-17T13:26:59.537528+09:00",
      "entry_price": 0.0001472,
      "current_pnl_pct": 0.0,
      "peak_pnl_pct": 0.0,
      "price_points": 19,
      "active_params": [
        "conservative",
        "current",
        "moderate",
        "tight",
        "aggressive",
        "wide_trail",
        "low_act",
        "micro"
      ],
      "score": 23.9342189251079,
      "grade": "D"
    },
    {
      "symbol": "PEPE",
      "entry_time": "2026-02-17T13:26:59.537910+09:00",
      "entry_price": 0.0001648,
      "current_pnl_pct": 0.0,
      "peak_pnl_pct": 0.0,
      "price_points": 19,
      "active_params": [
        "conservative",
        "current",
        "moderate",
        "tight",
        "aggressive",
        "wide_trail",
        "low_act",
        "micro"
      ],
      "score": 23.359149484766395,
      "grade": "D"
    },
    {
      "symbol": "SOL",
      "entry_time": "2026-02-17T13:28:08.286211+09:00",
      "entry_price": 0.002539,
      "current_pnl_pct": 0.0,
      "peak_pnl_pct": 0.0,
      "price_points": 13,
      "active_params": [
        "conservative",
        "current",
        "moderate",
        "tight",
        "aggressive",
        "wide_trail",
        "low_act",
        "micro"
      ],
      "score": 39.16091629990341,
      "grade": "C"
    },
    {
      "symbol": "PUMP",
      "entry_time": "2026-02-17T13:29:17.310615+09:00",
      "entry_price": 0.002249,
      "current_pnl_pct": 0.0,
      "peak_pnl_pct": 0.0,
      "price_points": 7,
      "active_params": [
        "conservative",
        "current",
        "moderate",
        "tight",
        "aggressive",
        "wide_trail",
        "low_act",
        "micro"
      ],
      "score": 39.02023412410112,
      "grade": "C"
    },
    {
      "symbol": "PUMP",
      "entry_time": "2026-02-17T13:29:17.311817+09:00",
      "entry_price": 0.006877,
      "current_pnl_pct": 0.0,
      "peak_pnl_pct": 0.0,
      "price_points": 7,
      "active_params": [
        "conservative",
        "current",
        "moderate",
        "tight",
        "aggressive",
        "wide_trail",
        "low_act",
        "micro"
      ],
      "score": 29.0,
      "grade": "D"
    },
    {
      "symbol": "PUMP",
      "entry_time": "2026-02-17T13:29:17.312407+09:00",
      "entry_price": 0.006879,
      "current_pnl_pct": 0.0,
      "peak_pnl_pct": 0.0,
      "price_points": 7,
      "active_params": [
        "conservative",
        "current",
        "moderate",
        "tight",
        "aggressive",
        "wide_trail",
        "low_act",
        "micro"
      ],
      "score": 29.0,
      "grade": "D"
    },
    {
      "symbol": "PUMP",
      "entry_time": "2026-02-17T13:29:17.312877+09:00",
      "entry_price": 0.008352,
      "current_pnl_pct": 0.0,
      "peak_pnl_pct": 0.0,
      "price_points": 7,
      "active_params": [
        "conservative",
        "current",
        "moderate",
        "tight",
        "aggressive",
        "wide_trail",
        "low_act",
        "micro"
      ],
      "score": 29.0,
      "grade": "D"
    }
  ],
  "recent_completed": [
    {
      "address": "He7QHEeSqNpCJ3UT3qQGAXX4gyqHWoYYJA3sc7unpump",
      "symbol": "Thiel",
      "entry_time": "2026-02-17T10:36:23.040264+09:00",
      "entry_price": 4.306e-05,
      "amount_usd": 20.0,
      "score": 62.50037098856012,
      "grade": "B",
      "liquidity": 16383.43,
      "volume_24h": 101579.07,
      "token_age_min": 12.0,
      "peak_pnl_pct": 21.97,
      "price_points": 16,
      "completed_at": "2026-02-17T10:39:15.337018+09:00",
      "results": {
        "conservative": {
          "act": 8.0,
          "trail": 3.0,
          "sl": -15.0,
          "exit_pnl_pct": 14.19,
          "exit_pnl_usd": 2.84,
          "exit_reason": "TRAIL",
          "exit_time": "2026-02-17T10:39:15.336103+09:00",
          "highest_pnl": 21.97,
          "trail_activated": true
        },
        "current": {
          "act": 5.0,
          "trail": 3.0,
          "sl": -15.0,
          "exit_pnl_pct": 14.19,
          "exit_pnl_usd": 2.84,
          "exit_reason": "TRAIL",
          "exit_time": "2026-02-17T10:39:15.336103+09:00",
          "highest_pnl": 21.97,
          "trail_activated": true
        },
        "moderate": {
          "act": 3.0,
          "trail": 2.0,
          "sl": -15.0,
          "exit_pnl_pct": 14.19,
          "exit_pnl_usd": 2.84,
          "exit_reason": "TRAIL",
          "exit_time": "2026-02-17T10:39:15.336103+09:00",
          "highest_pnl": 21.97,
          "trail_activated": true
        },
        "tight": {
          "act": 3.0,
          "trail": 1.5,
          "sl": -15.0,
          "exit_pnl_pct": 14.19,
          "exit_pnl_usd": 2.84,
          "exit_reason": "TRAIL",
          "exit_time": "2026-02-17T10:39:15.336103+09:00",
          "highest_pnl": 21.97,
          "trail_activated": true
        },
        "aggressive": {
          "act": 2.0,
          "trail": 1.0,
          "sl": -15.0,
          "exit_pnl_pct": 14.19,
          "exit_pnl_usd": 2.84,
          "exit_reason": "TRAIL",
          "exit_time": "2026-02-17T10:39:15.336103+09:00",
          "highest_pnl": 21.97,
          "trail_activated": true
        },
        "wide_trail": {
          "act": 5.0,
          "trail": 2.0,
          "sl": -15.0,
          "exit_pnl_pct": 14.19,
          "exit_pnl_usd": 2.84,
          "exit_reason": "TRAIL",
          "exit_time": "2026-02-17T10:39:15.336103+09:00",
          "highest_pnl": 21.97,
          "trail_activated": true
        },
        "low_act": {
          "act": 2.5,
          "trail": 1.5,
          "sl": -15.0,
          "exit_pnl_pct": 14.19,
          "exit_pnl_usd": 2.84,
          "exit_reason": "TRAIL",
          "exit_time": "2026-02-17T10:39:15.336103+09:00",
          "highest_pnl": 21.97,
          "trail_activated": true
        },
        "micro": {
          "act": 1.5,
          "trail": 0.8,
          "sl": -15.0,
          "exit_pnl_pct": 14.19,
          "exit_pnl_usd": 2.84,
          "exit_reason": "TRAIL",
          "exit_time": "2026-02-17T10:39:15.336103+09:00",
          "highest_pnl": 21.97,
          "trail_activated": true
        }
      }
    },
    {
      "address": "4o5Dmb9GYoz4SSzpiGCSfQAjr7eVK3RZYkdfoscupump",
      "symbol": "Wheelie",
      "entry_time": "2026-02-17T10:40:58.586854+09:00",
      "entry_price": 5.932e-05,
      "amount_usd": 20.0,
      "score": 64.83654704806804,
      "grade": "B",
      "liquidity": 19275.72,
      "volume_24h": 135176.89,
      "token_age_min": 6.0,
      "peak_pnl_pct": 0.0,
      "price_points": 7,
      "completed_at": "2026-02-17T10:42:08.720413+09:00",
      "results": {
        "conservative": {
          "act": 8.0,
          "trail": 3.0,
          "sl": -15.0,
          "exit_pnl_pct": -25.91,
          "exit_pnl_usd": -5.18,
          "exit_reason": "SL",
          "exit_time": "2026-02-17T10:42:08.719627+09:00",
          "highest_pnl": 0.0,
          "trail_activated": false
        },
        "current": {
          "act": 5.0,
          "trail": 3.0,
          "sl": -15.0,
          "exit_pnl_pct": -25.91,
          "exit_pnl_usd": -5.18,
          "exit_reason": "SL",
          "exit_time": "2026-02-17T10:42:08.719627+09:00",
          "highest_pnl": 0.0,
          "trail_activated": false
        },
        "moderate": {
          "act": 3.0,
          "trail": 2.0,
          "sl": -15.0,
          "exit_pnl_pct": -25.91,
          "exit_pnl_usd": -5.18,
          "exit_reason": "SL",
          "exit_time": "2026-02-17T10:42:08.719627+09:00",
          "highest_pnl": 0.0,
          "trail_activated": false
        },
        "tight": {
          "act": 3.0,
          "trail": 1.5,
          "sl": -15.0,
          "exit_pnl_pct": -25.91,
          "exit_pnl_usd": -5.18,
          "exit_reason": "SL",
          "exit_time": "2026-02-17T10:42:08.719627+09:00",
          "highest_pnl": 0.0,
          "trail_activated": false
        },
        "aggressive": {
          "act": 2.0,
          "trail": 1.0,
          "sl": -15.0,
          "exit_pnl_pct": -25.91,
          "exit_pnl_usd": -5.18,
          "exit_reason": "SL",
          "exit_time": "2026-02-17T10:42:08.719627+09:00",
          "highest_pnl": 0.0,
          "trail_activated": false
        },
        "wide_trail": {
          "act": 5.0,
          "trail": 2.0,
          "sl": -15.0,
          "exit_pnl_pct": -25.91,
          "exit_pnl_usd": -5.18,
          "exit_reason": "SL",
          "exit_time": "2026-02-17T10:42:08.719627+09:00",
          "highest_pnl": 0.0,
          "trail_activated": false
        },
        "low_act": {
          "act": 2.5,
          "trail": 1.5,
          "sl": -15.0,
          "exit_pnl_pct": -25.91,
          "exit_pnl_usd": -5.18,
          "exit_reason": "SL",
          "exit_time": "2026-02-17T10:42:08.719627+09:00",
          "highest_pnl": 0.0,
          "trail_activated": false
        },
        "micro": {
          "act": 1.5,
          "trail": 0.8,
          "sl": -15.0,
          "exit_pnl_pct": -25.91,
          "exit_pnl_usd": -5.18,
          "exit_reason": "SL",
          "exit_time": "2026-02-17T10:42:08.719627+09:00",
          "highest_pnl": 0.0,
          "trail_activated": false
        }
      }
    },
    {
      "address": "97HSzZDCBiNEKGxdXZYqFsKL83qRnhPbun8tE5rApump",
      "symbol": "FLOYDPUNCH",
      "entry_time": "2026-02-17T10:51:15.751682+09:00",
      "entry_price": 0.0001366,
      "amount_usd": 20.0,
      "score": 72.61199433414494,
      "grade": "A",
      "liquidity": 30037.55,
      "volume_24h": 461894.06,
      "token_age_min": 60.0,
      "peak_pnl_pct": 31.55,
      "price_points": 10,
      "completed_at": "2026-02-17T10:52:58.137330+09:00",
      "results": {
        "conservative": {
          "act": 8.0,
          "trail": 3.0,
          "sl": -15.0,
          "exit_pnl_pct": 8.57,
          "exit_pnl_usd": 1.71,
          "exit_reason": "TRAIL",
          "exit_time": "2026-02-17T10:52:58.136368+09:00",
          "highest_pnl": 31.55,
          "trail_activated": true
        },
        "current": {
          "act": 5.0,
          "trail": 3.0,
          "sl": -15.0,
          "exit_pnl_pct": 8.57,
          "exit_pnl_usd": 1.71,
          "exit_reason": "TRAIL",
          "exit_time": "2026-02-17T10:52:58.136368+09:00",
          "highest_pnl": 31.55,
          "trail_activated": true
        },
        "moderate": {
          "act": 3.0,
          "trail": 2.0,
          "sl": -15.0,
          "exit_pnl_pct": 8.57,
          "exit_pnl_usd": 1.71,
          "exit_reason": "TRAIL",
          "exit_time": "2026-02-17T10:52:58.136368+09:00",
          "highest_pnl": 31.55,
          "trail_activated": true
        },
        "tight": {
          "act": 3.0,
          "trail": 1.5,
          "sl": -15.0,
          "exit_pnl_pct": 8.57,
          "exit_pnl_usd": 1.71,
          "exit_reason": "TRAIL",
          "exit_time": "2026-02-17T10:52:58.136368+09:00",
          "highest_pnl": 31.55,
          "trail_activated": true
        },
        "aggressive": {
          "act": 2.0,
          "trail": 1.0,
          "sl": -15.0,
          "exit_pnl_pct": 8.57,
          "exit_pnl_usd": 1.71,
          "exit_reason": "TRAIL",
          "exit_time": "2026-02-17T10:52:58.136368+09:00",
          "highest_pnl": 31.55,
          "trail_activated": true
        },
        "wide_trail": {
          "act": 5.0,
          "trail": 2.0,
          "sl": -15.0,
          "exit_pnl_pct": 8.57,
          "exit_pnl_usd": 1.71,
          "exit_reason": "TRAIL",
          "exit_time": "2026-02-17T10:52:58.136368+09:00",
          "highest_pnl": 31.55,
          "trail_activated": true
        },
        "low_act": {
          "act": 2.5,
          "trail": 1.5,
          "sl": -15.0,
          "exit_pnl_pct": 8.57,
          "exit_pnl_usd": 1.71,
          "exit_reason": "TRAIL",
          "exit_time": "2026-02-17T10:52:58.136368+09:00",
          "highest_pnl": 31.55,
          "trail_activated": true
        },
        "micro": {
          "act": 1.5,
          "trail": 0.8,
          "sl": -15.0,
          "exit_pnl_pct": 8.57,
          "exit_pnl_usd": 1.71,
          "exit_reason": "TRAIL",
          "exit_time": "2026-02-17T10:52:58.136368+09:00",
          "highest_pnl": 31.55,
          "trail_activated": true
        }
      }
    },
    {
      "address": "zDKbZj7M7nq36149rZFgfvNKGqBAnc5YyFgpEdApump",
      "symbol": "PRT",
      "entry_time": "2026-02-17T11:02:40.098509+09:00",
      "entry_price": 4.084e-05,
      "amount_usd": 20.0,
      "score": 61.46287975698966,
      "grade": "B",
      "liquidity": 15816.48,
      "volume_24h": 72852.51,
      "token_age_min": 12.0,
      "peak_pnl_pct": 10.11,
      "price_points": 7,
      "completed_at": "2026-02-17T11:03:50.721889+09:00",
      "results": {
        "conservative": {
          "act": 8.0,
          "trail": 3.0,
          "sl": -15.0,
          "exit_pnl_pct": -4.51,
          "exit_pnl_usd": -0.9,
          "exit_reason": "TRAIL",
          "exit_time": "2026-02-17T11:03:50.720953+09:00",
          "highest_pnl": 10.11,
          "trail_activated": true
        },
        "current": {
          "act": 5.0,
          "trail": 3.0,
          "sl": -15.0,
          "exit_pnl_pct": -4.51,
          "exit_pnl_usd": -0.9,
          "exit_reason": "TRAIL",
          "exit_time": "2026-02-17T11:03:50.720953+09:00",
          "highest_pnl": 10.11,
          "trail_activated": true
        },
        "moderate": {
          "act": 3.0,
          "trail": 2.0,
          "sl": -15.0,
          "exit_pnl_pct": -4.51,
          "exit_pnl_usd": -0.9,
          "exit_reason": "TRAIL",
          "exit_time": "2026-02-17T11:03:50.720953+09:00",
          "highest_pnl": 10.11,
          "trail_activated": true
        },
        "tight": {
          "act": 3.0,
          "trail": 1.5,
          "sl": -15.0,
          "exit_pnl_pct": -4.51,
          "exit_pnl_usd": -0.9,
          "exit_reason": "TRAIL",
          "exit_time": "2026-02-17T11:03:50.720953+09:00",
          "highest_pnl": 10.11,
          "trail_activated": true
        },
        "aggressive": {
          "act": 2.0,
          "trail": 1.0,
          "sl": -15.0,
          "exit_pnl_pct": -4.51,
          "exit_pnl_usd": -0.9,
          "exit_reason": "TRAIL",
          "exit_time": "2026-02-17T11:03:50.720953+09:00",
          "highest_pnl": 10.11,
          "trail_activated": true
        },
        "wide_trail": {
          "act": 5.0,
          "trail": 2.0,
          "sl": -15.0,
          "exit_pnl_pct": -4.51,
          "exit_pnl_usd": -0.9,
          "exit_reason": "TRAIL",
          "exit_time": "2026-02-17T11:03:50.720953+09:00",
          "highest_pnl": 10.11,
          "trail_activated": true
        },
        "low_act": {
          "act": 2.5,
          "trail": 1.5,
          "sl": -15.0,
          "exit_pnl_pct": -4.51,
          "exit_pnl_usd": -0.9,
          "exit_reason": "TRAIL",
          "exit_time": "2026-02-17T11:03:50.720953+09:00",
          "highest_pnl": 10.11,
          "trail_activated": true
        },
        "micro": {
          "act": 1.5,
          "trail": 0.8,
          "sl": -15.0,
          "exit_pnl_pct": -4.51,
          "exit_pnl_usd": -0.9,
          "exit_reason": "TRAIL",
          "exit_time": "2026-02-17T11:03:50.720953+09:00",
          "highest_pnl": 10.11,
          "trail_activated": true
        }
      }
    },
    {
      "address": "H4DUHRWq2qpLPK65h4WBq1sbUNoNNhxBPyoJ633wpump",
      "symbol": "BILL",
      "entry_time": "2026-02-17T11:23:11.302882+09:00",
      "entry_price": 7.311e-05,
      "amount_usd": 20.0,
      "score": 65.66978652038354,
      "grade": "A",
      "liquidity": 21343.74,
      "volume_24h": 139685.21,
      "token_age_min": 6.0,
      "peak_pnl_pct": 0.0,
      "price_points": 4,
      "completed_at": "2026-02-17T11:23:44.618885+09:00",
      "results": {
        "conservative": {
          "act": 8.0,
          "trail": 3.0,
          "sl": -15.0,
          "exit_pnl_pct": -28.61,
          "exit_pnl_usd": -5.72,
          "exit_reason": "SL",
          "exit_time": "2026-02-17T11:23:44.618000+09:00",
          "highest_pnl": 0.0,
          "trail_activated": false
        },
        "current": {
          "act": 5.0,
          "trail": 3.0,
          "sl": -15.0,
          "exit_pnl_pct": -28.61,
          "exit_pnl_usd": -5.72,
          "exit_reason": "SL",
          "exit_time": "2026-02-17T11:23:44.618000+09:00",
          "highest_pnl": 0.0,
          "trail_activated": false
        },
        "moderate": {
          "act": 3.0,
          "trail": 2.0,
          "sl": -15.0,
          "exit_pnl_pct": -28.61,
          "exit_pnl_usd": -5.72,
          "exit_reason": "SL",
          "exit_time": "2026-02-17T11:23:44.618000+09:00",
          "highest_pnl": 0.0,
          "trail_activated": false
        },
        "tight": {
          "act": 3.0,
          "trail": 1.5,
          "sl": -15.0,
          "exit_pnl_pct": -28.61,
          "exit_pnl_usd": -5.72,
          "exit_reason": "SL",
          "exit_time": "2026-02-17T11:23:44.618000+09:00",
          "highest_pnl": 0.0,
          "trail_activated": false
        },
        "aggressive": {
          "act": 2.0,
          "trail": 1.0,
          "sl": -15.0,
          "exit_pnl_pct": -28.61,
          "exit_pnl_usd": -5.72,
          "exit_reason": "SL",
          "exit_time": "2026-02-17T11:23:44.618000+09:00",
          "highest_pnl": 0.0,
          "trail_activated": false
        },
        "wide_trail": {
          "act": 5.0,
          "trail": 2.0,
          "sl": -15.0,
          "exit_pnl_pct": -28.61,
          "exit_pnl_usd": -5.72,
          "exit_reason": "SL",
          "exit_time": "2026-02-17T11:23:44.618000+09:00",
          "highest_pnl": 0.0,
          "trail_activated": false
        },
        "low_act": {
          "act": 2.5,
          "trail": 1.5,
          "sl": -15.0,
          "exit_pnl_pct": -28.61,
          "exit_pnl_usd": -5.72,
          "exit_reason": "SL",
          "exit_time": "2026-02-17T11:23:44.618000+09:00",
          "highest_pnl": 0.0,
          "trail_activated": false
        },
        "micro": {
          "act": 1.5,
          "trail": 0.8,
          "sl": -15.0,
          "exit_pnl_pct": -28.61,
          "exit_pnl_usd": -5.72,
          "exit_reason": "SL",
          "exit_time": "2026-02-17T11:23:44.618000+09:00",
          "highest_pnl": 0.0,
          "trail_activated": false
        }
      }
    },
    {
      "address": "7sShzRXuv4Z19QdmJffJTnL6r2PC8EPTQ8aUndQipump",
      "symbol": "LUNAR",
      "entry_time": "2026-02-17T09:51:11.814321+09:00",
      "entry_price": 0.003914,
      "amount_usd": 20.0,
      "score": 73.5680870039695,
      "grade": "A",
      "liquidity": 155456.4,
      "volume_24h": 300861.65,
      "token_age_min": 42.0,
      "peak_pnl_pct": 15.0,
      "price_points": 553,
      "completed_at": "2026-02-17T11:37:41.234571+09:00",
      "results": {
        "conservative": {
          "act": 8.0,
          "trail": 3.0,
          "sl": -15.0,
          "exit_pnl_pct": 11.62,
          "exit_pnl_usd": 2.32,
          "exit_reason": "TRAIL",
          "exit_time": "2026-02-17T11:37:41.233902+09:00",
          "highest_pnl": 15.0,
          "trail_activated": true
        },
        "current": {
          "act": 5.0,
          "trail": 3.0,
          "sl": -15.0,
          "exit_pnl_pct": 3.7,
          "exit_pnl_usd": 0.74,
          "exit_reason": "TRAIL",
          "exit_time": "2026-02-17T10:42:08.718836+09:00",
          "highest_pnl": 6.8,
          "trail_activated": true
        },
        "moderate": {
          "act": 3.0,
          "trail": 2.0,
          "sl": -15.0,
          "exit_pnl_pct": 4.34,
          "exit_pnl_usd": 0.87,
          "exit_reason": "TRAIL",
          "exit_time": "2026-02-17T10:41:32.151820+09:00",
          "highest_pnl": 6.8,
          "trail_activated": true
        },
        "tight": {
          "act": 3.0,
          "trail": 1.5,
          "sl": -15.0,
          "exit_pnl_pct": 4.34,
          "exit_pnl_usd": 0.87,
          "exit_reason": "TRAIL",
          "exit_time": "2026-02-17T10:41:32.151820+09:00",
          "highest_pnl": 6.8,
          "trail_activated": true
        },
        "aggressive": {
          "act": 2.0,
          "trail": 1.0,
          "sl": -15.0,
          "exit_pnl_pct": 1.07,
          "exit_pnl_usd": 0.21,
          "exit_reason": "TRAIL",
          "exit_time": "2026-02-17T10:27:54.599449+09:00",
          "highest_pnl": 2.45,
          "trail_activated": true
        },
        "wide_trail": {
          "act": 5.0,
          "trail": 2.0,
          "sl": -15.0,
          "exit_pnl_pct": 4.34,
          "exit_pnl_usd": 0.87,
          "exit_reason": "TRAIL",
          "exit_time": "2026-02-17T10:41:32.151820+09:00",
          "highest_pnl": 6.8,
          "trail_activated": true
        },
        "low_act": {
          "act": 2.5,
          "trail": 1.5,
          "sl": -15.0,
          "exit_pnl_pct": 4.34,
          "exit_pnl_usd": 0.87,
          "exit_reason": "TRAIL",
          "exit_time": "2026-02-17T10:41:32.151820+09:00",
          "highest_pnl": 6.8,
          "trail_activated": true
        },
        "micro": {
          "act": 1.5,
          "trail": 0.8,
          "sl": -15.0,
          "exit_pnl_pct": 1.56,
          "exit_pnl_usd": 0.31,
          "exit_reason": "TRAIL",
          "exit_time": "2026-02-17T10:27:21.783226+09:00",
          "highest_pnl": 2.45,
          "trail_activated": true
        }
      }
    },
    {
      "address": "EqsJxXXR9kdCUvuXBY4hadqs89AwbyRHgxnvPm8Xpump",
      "symbol": "CAMPBELL",
      "entry_time": "2026-02-17T11:15:11.723333+09:00",
      "entry_price": 0.000819,
      "amount_usd": 20.0,
      "score": 60.03489897321667,
      "grade": "B",
      "liquidity": 75310.82,
      "volume_24h": 1246285.96,
      "token_age_min": 1074.0,
      "peak_pnl_pct": 19.52,
      "price_points": 144,
      "completed_at": "2026-02-17T11:42:30.918452+09:00",
      "results": {
        "conservative": {
          "act": 8.0,
          "trail": 3.0,
          "sl": -15.0,
          "exit_pnl_pct": 16.48,
          "exit_pnl_usd": 3.3,
          "exit_reason": "TRAIL",
          "exit_time": "2026-02-17T11:42:30.916968+09:00",
          "highest_pnl": 19.52,
          "trail_activated": true
        },
        "current": {
          "act": 5.0,
          "trail": 3.0,
          "sl": -15.0,
          "exit_pnl_pct": 16.48,
          "exit_pnl_usd": 3.3,
          "exit_reason": "TRAIL",
          "exit_time": "2026-02-17T11:42:30.916968+09:00",
          "highest_pnl": 19.52,
          "trail_activated": true
        },
        "moderate": {
          "act": 3.0,
          "trail": 2.0,
          "sl": -15.0,
          "exit_pnl_pct": 10.48,
          "exit_pnl_usd": 2.1,
          "exit_reason": "TRAIL",
          "exit_time": "2026-02-17T11:39:04.926761+09:00",
          "highest_pnl": 12.66,
          "trail_activated": true
        },
        "tight": {
          "act": 3.0,
          "trail": 1.5,
          "sl": -15.0,
          "exit_pnl_pct": 1.49,
          "exit_pnl_usd": 0.3,
          "exit_reason": "TRAIL",
          "exit_time": "2026-02-17T11:22:36.409231+09:00",
          "highest_pnl": 3.06,
          "trail_activated": true
        },
        "aggressive": {
          "act": 2.0,
          "trail": 1.0,
          "sl": -15.0,
          "exit_pnl_pct": 1.79,
          "exit_pnl_usd": 0.36,
          "exit_reason": "TRAIL",
          "exit_time": "2026-02-17T11:21:28.244181+09:00",
          "highest_pnl": 3.06,
          "trail_activated": true
        },
        "wide_trail": {
          "act": 5.0,
          "trail": 2.0,
          "sl": -15.0,
          "exit_pnl_pct": 10.48,
          "exit_pnl_usd": 2.1,
          "exit_reason": "TRAIL",
          "exit_time": "2026-02-17T11:39:04.926761+09:00",
          "highest_pnl": 12.66,
          "trail_activated": true
        },
        "low_act": {
          "act": 2.5,
          "trail": 1.5,
          "sl": -15.0,
          "exit_pnl_pct": 1.49,
          "exit_pnl_usd": 0.3,
          "exit_reason": "TRAIL",
          "exit_time": "2026-02-17T11:22:36.409231+09:00",
          "highest_pnl": 3.06,
          "trail_activated": true
        },
        "micro": {
          "act": 1.5,
          "trail": 0.8,
          "sl": -15.0,
          "exit_pnl_pct": 1.79,
          "exit_pnl_usd": 0.36,
          "exit_reason": "TRAIL",
          "exit_time": "2026-02-17T11:21:28.244181+09:00",
          "highest_pnl": 3.06,
          "trail_activated": true
        }
      }
    },
    {
      "address": "8yY8WDr1Ng3Vcf2d458z4EjKGt1PtnizT1Ntr9jxpump",
      "symbol": "Knight",
      "entry_time": "2026-02-17T11:37:55.327437+09:00",
      "entry_price": 3.97e-05,
      "amount_usd": 20.0,
      "score": 65.75692170248928,
      "grade": "A",
      "liquidity": 15726.96,
      "volume_24h": 99529.18,
      "token_age_min": 30.0,
      "peak_pnl_pct": 0.0,
      "price_points": 25,
      "completed_at": "2026-02-17T11:42:30.919069+09:00",
      "results": {
        "conservative": {
          "act": 8.0,
          "trail": 3.0,
          "sl": -15.0,
          "exit_pnl_pct": -21.01,
          "exit_pnl_usd": -4.2,
          "exit_reason": "SL",
          "exit_time": "2026-02-17T11:42:30.917742+09:00",
          "highest_pnl": 0.0,
          "trail_activated": false
        },
        "current": {
          "act": 5.0,
          "trail": 3.0,
          "sl": -15.0,
          "exit_pnl_pct": -21.01,
          "exit_pnl_usd": -4.2,
          "exit_reason": "SL",
          "exit_time": "2026-02-17T11:42:30.917742+09:00",
          "highest_pnl": 0.0,
          "trail_activated": false
        },
        "moderate": {
          "act": 3.0,
          "trail": 2.0,
          "sl": -15.0,
          "exit_pnl_pct": -21.01,
          "exit_pnl_usd": -4.2,
          "exit_reason": "SL",
          "exit_time": "2026-02-17T11:42:30.917742+09:00",
          "highest_pnl": 0.0,
          "trail_activated": false
        },
        "tight": {
          "act": 3.0,
          "trail": 1.5,
          "sl": -15.0,
          "exit_pnl_pct": -21.01,
          "exit_pnl_usd": -4.2,
          "exit_reason": "SL",
          "exit_time": "2026-02-17T11:42:30.917742+09:00",
          "highest_pnl": 0.0,
          "trail_activated": false
        },
        "aggressive": {
          "act": 2.0,
          "trail": 1.0,
          "sl": -15.0,
          "exit_pnl_pct": -21.01,
          "exit_pnl_usd": -4.2,
          "exit_reason": "SL",
          "exit_time": "2026-02-17T11:42:30.917742+09:00",
          "highest_pnl": 0.0,
          "trail_activated": false
        },
        "wide_trail": {
          "act": 5.0,
          "trail": 2.0,
          "sl": -15.0,
          "exit_pnl_pct": -21.01,
          "exit_pnl_usd": -4.2,
          "exit_reason": "SL",
          "exit_time": "2026-02-17T11:42:30.917742+09:00",
          "highest_pnl": 0.0,
          "trail_activated": false
        },
        "low_act": {
          "act": 2.5,
          "trail": 1.5,
          "sl": -15.0,
          "exit_pnl_pct": -21.01,
          "exit_pnl_usd": -4.2,
          "exit_reason": "SL",
          "exit_time": "2026-02-17T11:42:30.917742+09:00",
          "highest_pnl": 0.0,
          "trail_activated": false
        },
        "micro": {
          "act": 1.5,
          "trail": 0.8,
          "sl": -15.0,
          "exit_pnl_pct": -21.01,
          "exit_pnl_usd": -4.2,
          "exit_reason": "SL",
          "exit_time": "2026-02-17T11:42:30.917742+09:00",
          "highest_pnl": 0.0,
          "trail_activated": false
        }
      }
    },
    {
      "address": "GXVRRBJuoErp7G75EpzNHzpBo1fg84bEjxiUF1Gcpump",
      "symbol": "Buddy",
      "entry_time": "2026-02-17T11:58:32.930177+09:00",
      "entry_price": 4.242e-05,
      "amount_usd": 20.0,
      "score": 66.58694702342382,
      "grade": "A",
      "liquidity": 16243.74,
      "volume_24h": 116305.47,
      "token_age_min": 48.0,
      "peak_pnl_pct": 11.29,
      "price_points": 16,
      "completed_at": "2026-02-17T12:01:24.115602+09:00",
      "results": {
        "conservative": {
          "act": 8.0,
          "trail": 3.0,
          "sl": -15.0,
          "exit_pnl_pct": 2.76,
          "exit_pnl_usd": 0.55,
          "exit_reason": "TRAIL",
          "exit_time": "2026-02-17T12:01:24.114630+09:00",
          "highest_pnl": 11.29,
          "trail_activated": true
        },
        "current": {
          "act": 5.0,
          "trail": 3.0,
          "sl": -15.0,
          "exit_pnl_pct": 2.76,
          "exit_pnl_usd": 0.55,
          "exit_reason": "TRAIL",
          "exit_time": "2026-02-17T12:01:24.114630+09:00",
          "highest_pnl": 11.29,
          "trail_activated": true
        },
        "moderate": {
          "act": 3.0,
          "trail": 2.0,
          "sl": -15.0,
          "exit_pnl_pct": 2.76,
          "exit_pnl_usd": 0.55,
          "exit_reason": "TRAIL",
          "exit_time": "2026-02-17T12:01:24.114630+09:00",
          "highest_pnl": 11.29,
          "trail_activated": true
        },
        "tight": {
          "act": 3.0,
          "trail": 1.5,
          "sl": -15.0,
          "exit_pnl_pct": 2.76,
          "exit_pnl_usd": 0.55,
          "exit_reason": "TRAIL",
          "exit_time": "2026-02-17T12:01:24.114630+09:00",
          "highest_pnl": 11.29,
          "trail_activated": true
        },
        "aggressive": {
          "act": 2.0,
          "trail": 1.0,
          "sl": -15.0,
          "exit_pnl_pct": 2.76,
          "exit_pnl_usd": 0.55,
          "exit_reason": "TRAIL",
          "exit_time": "2026-02-17T12:01:24.114630+09:00",
          "highest_pnl": 11.29,
          "trail_activated": true
        },
        "wide_trail": {
          "act": 5.0,
          "trail": 2.0,
          "sl": -15.0,
          "exit_pnl_pct": 2.76,
          "exit_pnl_usd": 0.55,
          "exit_reason": "TRAIL",
          "exit_time": "2026-02-17T12:01:24.114630+09:00",
          "highest_pnl": 11.29,
          "trail_activated": true
        },
        "low_act": {
          "act": 2.5,
          "trail": 1.5,
          "sl": -15.0,
          "exit_pnl_pct": 2.76,
          "exit_pnl_usd": 0.55,
          "exit_reason": "TRAIL",
          "exit_time": "2026-02-17T12:01:24.114630+09:00",
          "highest_pnl": 11.29,
          "trail_activated": true
        },
        "micro": {
          "act": 1.5,
          "trail": 0.8,
          "sl": -15.0,
          "exit_pnl_pct": 2.76,
          "exit_pnl_usd": 0.55,
          "exit_reason": "TRAIL",
          "exit_time": "2026-02-17T12:01:24.114630+09:00",
          "highest_pnl": 11.29,
          "trail_activated": true
        }
      }
    },
    {
      "address": "BNrqaa72k8omrZwbyW6V2HPdUt2gRKizkqguYJSGpump",
      "symbol": "Smile",
      "entry_time": "2026-02-17T12:06:35.652853+09:00",
      "entry_price": 5.036e-05,
      "amount_usd": 20.0,
      "score": 61.61335295661376,
      "grade": "B",
      "liquidity": 17799.38,
      "volume_24h": 146318.46,
      "token_age_min": 12.0,
      "peak_pnl_pct": 74.44,
      "price_points": 16,
      "completed_at": "2026-02-17T12:09:26.404248+09:00",
      "results": {
        "conservative": {
          "act": 8.0,
          "trail": 3.0,
          "sl": -15.0,
          "exit_pnl_pct": 55.42,
          "exit_pnl_usd": 11.08,
          "exit_reason": "TRAIL",
          "exit_time": "2026-02-17T12:09:26.403802+09:00",
          "highest_pnl": 74.44,
          "trail_activated": true
        },
        "current": {
          "act": 5.0,
          "trail": 3.0,
          "sl": -15.0,
          "exit_pnl_pct": 55.42,
          "exit_pnl_usd": 11.08,
          "exit_reason": "TRAIL",
          "exit_time": "2026-02-17T12:09:26.403802+09:00",
          "highest_pnl": 74.44,
          "trail_activated": true
        },
        "moderate": {
          "act": 3.0,
          "trail": 2.0,
          "sl": -15.0,
          "exit_pnl_pct": 55.42,
          "exit_pnl_usd": 11.08,
          "exit_reason": "TRAIL",
          "exit_time": "2026-02-17T12:09:26.403802+09:00",
          "highest_pnl": 74.44,
          "trail_activated": true
        },
        "tight": {
          "act": 3.0,
          "trail": 1.5,
          "sl": -15.0,
          "exit_pnl_pct": 55.42,
          "exit_pnl_usd": 11.08,
          "exit_reason": "TRAIL",
          "exit_time": "2026-02-17T12:09:26.403802+09:00",
          "highest_pnl": 74.44,
          "trail_activated": true
        },
        "aggressive": {
          "act": 2.0,
          "trail": 1.0,
          "sl": -15.0,
          "exit_pnl_pct": 55.42,
          "exit_pnl_usd": 11.08,
          "exit_reason": "TRAIL",
          "exit_time": "2026-02-17T12:09:26.403802+09:00",
          "highest_pnl": 74.44,
          "trail_activated": true
        },
        "wide_trail": {
          "act": 5.0,
          "trail": 2.0,
          "sl": -15.0,
          "exit_pnl_pct": 55.42,
          "exit_pnl_usd": 11.08,
          "exit_reason": "TRAIL",
          "exit_time": "2026-02-17T12:09:26.403802+09:00",
          "highest_pnl": 74.44,
          "trail_activated": true
        },
        "low_act": {
          "act": 2.5,
          "trail": 1.5,
          "sl": -15.0,
          "exit_pnl_pct": 55.42,
          "exit_pnl_usd": 11.08,
          "exit_reason": "TRAIL",
          "exit_time": "2026-02-17T12:09:26.403802+09:00",
          "highest_pnl": 74.44,
          "trail_activated": true
        },
        "micro": {
          "act": 1.5,
          "trail": 0.8,
          "sl": -15.0,
          "exit_pnl_pct": 55.42,
          "exit_pnl_usd": 11.08,
          "exit_reason": "TRAIL",
          "exit_time": "2026-02-17T12:09:26.403802+09:00",
          "highest_pnl": 74.44,
          "trail_activated": true
        }
      }
    },
    {
      "address": "CSFXDnaA4bhZVzn4bkBdwbootCedgT4PKcEYBsNGpump",
      "symbol": "Community",
      "entry_time": "2026-02-17T12:32:51.218625+09:00",
      "entry_price": 5.18e-05,
      "amount_usd": 20.0,
      "score": 61.13436394792549,
      "grade": "B",
      "liquidity": 17909.87,
      "volume_24h": 66662.58,
      "token_age_min": 6.0,
      "peak_pnl_pct": 3.28,
      "price_points": 10,
      "pc_5m": -1.5,
      "pc_1h": 51.41,
      "buys_1h": 1097,
      "sells_1h": 860,
      "bs_ratio": 1.28,
      "completed_at": "2026-02-17T12:34:34.285166+09:00",
      "results": {
        "conservative": {
          "act": 8.0,
          "trail": 3.0,
          "sl": -15.0,
          "exit_pnl_pct": -19.17,
          "exit_pnl_usd": -3.83,
          "exit_reason": "SL",
          "exit_time": "2026-02-17T12:34:34.284687+09:00",
          "highest_pnl": 0.0,
          "trail_activated": false
        },
        "current": {
          "act": 5.0,
          "trail": 3.0,
          "sl": -15.0,
          "exit_pnl_pct": -19.17,
          "exit_pnl_usd": -3.83,
          "exit_reason": "SL",
          "exit_time": "2026-02-17T12:34:34.284687+09:00",
          "highest_pnl": 0.0,
          "trail_activated": false
        },
        "moderate": {
          "act": 3.0,
          "trail": 2.0,
          "sl": -15.0,
          "exit_pnl_pct": -10.75,
          "exit_pnl_usd": -2.15,
          "exit_reason": "TRAIL",
          "exit_time": "2026-02-17T12:34:01.531061+09:00",
          "highest_pnl": 3.28,
          "trail_activated": true
        },
        "tight": {
          "act": 3.0,
          "trail": 1.5,
          "sl": -15.0,
          "exit_pnl_pct": -10.75,
          "exit_pnl_usd": -2.15,
          "exit_reason": "TRAIL",
          "exit_time": "2026-02-17T12:34:01.531061+09:00",
          "highest_pnl": 3.28,
          "trail_activated": true
        },
        "aggressive": {
          "act": 2.0,
          "trail": 1.0,
          "sl": -15.0,
          "exit_pnl_pct": -10.75,
          "exit_pnl_usd": -2.15,
          "exit_reason": "TRAIL",
          "exit_time": "2026-02-17T12:34:01.531061+09:00",
          "highest_pnl": 3.28,
          "trail_activated": true
        },
        "wide_trail": {
          "act": 5.0,
          "trail": 2.0,
          "sl": -15.0,
          "exit_pnl_pct": -19.17,
          "exit_pnl_usd": -3.83,
          "exit_reason": "SL",
          "exit_time": "2026-02-17T12:34:34.284687+09:00",
          "highest_pnl": 0.0,
          "trail_activated": false
        },
        "low_act": {
          "act": 2.5,
          "trail": 1.5,
          "sl": -15.0,
          "exit_pnl_pct": -10.75,
          "exit_pnl_usd": -2.15,
          "exit_reason": "TRAIL",
          "exit_time": "2026-02-17T12:34:01.531061+09:00",
          "highest_pnl": 3.28,
          "trail_activated": true
        },
        "micro": {
          "act": 1.5,
          "trail": 0.8,
          "sl": -15.0,
          "exit_pnl_pct": -10.75,
          "exit_pnl_usd": -2.15,
          "exit_reason": "TRAIL",
          "exit_time": "2026-02-17T12:34:01.531061+09:00",
          "highest_pnl": 3.28,
          "trail_activated": true
        }
      }
    },
    {
      "address": "4rWuWZei2iFNHYpnz5wjMeSvimsJcj5EgpSNvNS1pump",
      "symbol": "SAID",
      "entry_time": "2026-02-17T12:39:44.324744+09:00",
      "entry_price": 0.0003807,
      "amount_usd": 20.0,
      "score": 69.72919539379038,
      "grade": "A",
      "liquidity": 49026.75,
      "volume_24h": 284057.58,
      "token_age_min": 30.0,
      "peak_pnl_pct": 6.99,
      "price_points": 22,
      "pc_5m": 33.5,
      "pc_1h": 939.0,
      "buys_1h": 2242,
      "sells_1h": 2009,
      "bs_ratio": 1.12,
      "completed_at": "2026-02-17T12:43:47.257692+09:00",
      "results": {
        "conservative": {
          "act": 8.0,
          "trail": 3.0,
          "sl": -15.0,
          "exit_pnl_pct": -16.63,
          "exit_pnl_usd": -3.33,
          "exit_reason": "SL",
          "exit_time": "2026-02-17T12:43:47.257360+09:00",
          "highest_pnl": 0.0,
          "trail_activated": false
        },
        "current": {
          "act": 5.0,
          "trail": 3.0,
          "sl": -15.0,
          "exit_pnl_pct": 0.24,
          "exit_pnl_usd": 0.05,
          "exit_reason": "TRAIL",
          "exit_time": "2026-02-17T12:40:55.757135+09:00",
          "highest_pnl": 6.99,
          "trail_activated": true
        },
        "moderate": {
          "act": 3.0,
          "trail": 2.0,
          "sl": -15.0,
          "exit_pnl_pct": 0.24,
          "exit_pnl_usd": 0.05,
          "exit_reason": "TRAIL",
          "exit_time": "2026-02-17T12:40:55.757135+09:00",
          "highest_pnl": 6.99,
          "trail_activated": true
        },
        "tight": {
          "act": 3.0,
          "trail": 1.5,
          "sl": -15.0,
          "exit_pnl_pct": 0.24,
          "exit_pnl_usd": 0.05,
          "exit_reason": "TRAIL",
          "exit_time": "2026-02-17T12:40:55.757135+09:00",
          "highest_pnl": 6.99,
          "trail_activated": true
        },
        "aggressive": {
          "act": 2.0,
          "trail": 1.0,
          "sl": -15.0,
          "exit_pnl_pct": 0.24,
          "exit_pnl_usd": 0.05,
          "exit_reason": "TRAIL",
          "exit_time": "2026-02-17T12:40:55.757135+09:00",
          "highest_pnl": 6.99,
          "trail_activated": true
        },
        "wide_trail": {
          "act": 5.0,
          "trail": 2.0,
          "sl": -15.0,
          "exit_pnl_pct": 0.24,
          "exit_pnl_usd": 0.05,
          "exit_reason": "TRAIL",
          "exit_time": "2026-02-17T12:40:55.757135+09:00",
          "highest_pnl": 6.99,
          "trail_activated": true
        },
        "low_act": {
          "act": 2.5,
          "trail": 1.5,
          "sl": -15.0,
          "exit_pnl_pct": 0.24,
          "exit_pnl_usd": 0.05,
          "exit_reason": "TRAIL",
          "exit_time": "2026-02-17T12:40:55.757135+09:00",
          "highest_pnl": 6.99,
          "trail_activated": true
        },
        "micro": {
          "act": 1.5,
          "trail": 0.8,
          "sl": -15.0,
          "exit_pnl_pct": 0.24,
          "exit_pnl_usd": 0.05,
          "exit_reason": "TRAIL",
          "exit_time": "2026-02-17T12:40:55.757135+09:00",
          "highest_pnl": 6.99,
          "trail_activated": true
        }
      }
    },
    {
      "address": "Dt63XCUTW2va19GikbrBexbk2QEBoE8Zyx6AKduepump",
      "symbol": "OceanKid",
      "entry_time": "2026-02-17T12:46:40.519661+09:00",
      "entry_price": 6.051e-05,
      "amount_usd": 20.0,
      "score": 66.23636758616502,
      "grade": "A",
      "liquidity": 19353.84,
      "volume_24h": 79376.49,
      "token_age_min": 6.0,
      "peak_pnl_pct": 11.44,
      "price_points": 4,
      "pc_5m": 56.52,
      "pc_1h": 66.33,
      "buys_1h": 1082,
      "sells_1h": 816,
      "bs_ratio": 1.33,
      "completed_at": "2026-02-17T12:47:14.778167+09:00",
      "results": {
        "conservative": {
          "act": 8.0,
          "trail": 3.0,
          "sl": -15.0,
          "exit_pnl_pct": -28.62,
          "exit_pnl_usd": -5.72,
          "exit_reason": "SL",
          "exit_time": "2026-02-17T12:47:14.777282+09:00",
          "highest_pnl": 11.44,
          "trail_activated": true
        },
        "current": {
          "act": 5.0,
          "trail": 3.0,
          "sl": -15.0,
          "exit_pnl_pct": -28.62,
          "exit_pnl_usd": -5.72,
          "exit_reason": "SL",
          "exit_time": "2026-02-17T12:47:14.777282+09:00",
          "highest_pnl": 11.44,
          "trail_activated": true
        },
        "moderate": {
          "act": 3.0,
          "trail": 2.0,
          "sl": -15.0,
          "exit_pnl_pct": -28.62,
          "exit_pnl_usd": -5.72,
          "exit_reason": "SL",
          "exit_time": "2026-02-17T12:47:14.777282+09:00",
          "highest_pnl": 11.44,
          "trail_activated": true
        },
        "tight": {
          "act": 3.0,
          "trail": 1.5,
          "sl": -15.0,
          "exit_pnl_pct": -28.62,
          "exit_pnl_usd": -5.72,
          "exit_reason": "SL",
          "exit_time": "2026-02-17T12:47:14.777282+09:00",
          "highest_pnl": 11.44,
          "trail_activated": true
        },
        "aggressive": {
          "act": 2.0,
          "trail": 1.0,
          "sl": -15.0,
          "exit_pnl_pct": -28.62,
          "exit_pnl_usd": -5.72,
          "exit_reason": "SL",
          "exit_time": "2026-02-17T12:47:14.777282+09:00",
          "highest_pnl": 11.44,
          "trail_activated": true
        },
        "wide_trail": {
          "act": 5.0,
          "trail": 2.0,
          "sl": -15.0,
          "exit_pnl_pct": -28.62,
          "exit_pnl_usd": -5.72,
          "exit_reason": "SL",
          "exit_time": "2026-02-17T12:47:14.777282+09:00",
          "highest_pnl": 11.44,
          "trail_activated": true
        },
        "low_act": {
          "act": 2.5,
          "trail": 1.5,
          "sl": -15.0,
          "exit_pnl_pct": -28.62,
          "exit_pnl_usd": -5.72,
          "exit_reason": "SL",
          "exit_time": "2026-02-17T12:47:14.777282+09:00",
          "highest_pnl": 11.44,
          "trail_activated": true
        },
        "micro": {
          "act": 1.5,
          "trail": 0.8,
          "sl": -15.0,
          "exit_pnl_pct": -28.62,
          "exit_pnl_usd": -5.72,
          "exit_reason": "SL",
          "exit_time": "2026-02-17T12:47:14.777282+09:00",
          "highest_pnl": 11.44,
          "trail_activated": true
        }
      }
    },
    {
      "address": "3dL1wQJE8wim69rHAxb2GAvpyXTupoma33pHWbeBpump",
      "symbol": "PONYTA",
      "entry_time": "2026-02-17T12:49:00.025459+09:00",
      "entry_price": 4.027e-05,
      "amount_usd": 20.0,
      "score": 61.64325216567726,
      "grade": "B",
      "liquidity": 15709.84,
      "volume_24h": 77115.43,
      "token_age_min": 18.0,
      "peak_pnl_pct": 7.18,
      "price_points": 10,
      "pc_5m": 28.07,
      "pc_1h": 12.92,
      "buys_1h": 1139,
      "sells_1h": 908,
      "bs_ratio": 1.25,
      "completed_at": "2026-02-17T12:50:42.768691+09:00",
      "results": {
        "conservative": {
          "act": 8.0,
          "trail": 3.0,
          "sl": -15.0,
          "exit_pnl_pct": -16.02,
          "exit_pnl_usd": -3.2,
          "exit_reason": "SL",
          "exit_time": "2026-02-17T12:50:42.768399+09:00",
          "highest_pnl": 0.0,
          "trail_activated": false
        },
        "current": {
          "act": 5.0,
          "trail": 3.0,
          "sl": -15.0,
          "exit_pnl_pct": -3.23,
          "exit_pnl_usd": -0.65,
          "exit_reason": "TRAIL",
          "exit_time": "2026-02-17T12:50:10.421327+09:00",
          "highest_pnl": 7.18,
          "trail_activated": true
        },
        "moderate": {
          "act": 3.0,
          "trail": 2.0,
          "sl": -15.0,
          "exit_pnl_pct": -3.23,
          "exit_pnl_usd": -0.65,
          "exit_reason": "TRAIL",
          "exit_time": "2026-02-17T12:50:10.421327+09:00",
          "highest_pnl": 7.18,
          "trail_activated": true
        },
        "tight": {
          "act": 3.0,
          "trail": 1.5,
          "sl": -15.0,
          "exit_pnl_pct": -3.23,
          "exit_pnl_usd": -0.65,
          "exit_reason": "TRAIL",
          "exit_time": "2026-02-17T12:50:10.421327+09:00",
          "highest_pnl": 7.18,
          "trail_activated": true
        },
        "aggressive": {
          "act": 2.0,
          "trail": 1.0,
          "sl": -15.0,
          "exit_pnl_pct": -3.23,
          "exit_pnl_usd": -0.65,
          "exit_reason": "TRAIL",
          "exit_time": "2026-02-17T12:50:10.421327+09:00",
          "highest_pnl": 7.18,
          "trail_activated": true
        },
        "wide_trail": {
          "act": 5.0,
          "trail": 2.0,
          "sl": -15.0,
          "exit_pnl_pct": -3.23,
          "exit_pnl_usd": -0.65,
          "exit_reason": "TRAIL",
          "exit_time": "2026-02-17T12:50:10.421327+09:00",
          "highest_pnl": 7.18,
          "trail_activated": true
        },
        "low_act": {
          "act": 2.5,
          "trail": 1.5,
          "sl": -15.0,
          "exit_pnl_pct": -3.23,
          "exit_pnl_usd": -0.65,
          "exit_reason": "TRAIL",
          "exit_time": "2026-02-17T12:50:10.421327+09:00",
          "highest_pnl": 7.18,
          "trail_activated": true
        },
        "micro": {
          "act": 1.5,
          "trail": 0.8,
          "sl": -15.0,
          "exit_pnl_pct": -3.23,
          "exit_pnl_usd": -0.65,
          "exit_reason": "TRAIL",
          "exit_time": "2026-02-17T12:50:10.421327+09:00",
          "highest_pnl": 7.18,
          "trail_activated": true
        }
      }
    },
    {
      "address": "DWnanVz8ogds4WuuRpFTBQ5gHRjQuUk2boMD8TVQpump",
      "symbol": "TRUMPIUS",
      "entry_time": "2026-02-17T11:58:32.928858+09:00",
      "entry_price": 0.005229,
      "amount_usd": 20.0,
      "score": 71.3320785402125,
      "grade": "A",
      "liquidity": 179918.05,
      "volume_24h": 185992.91,
      "token_age_min": 18.0,
      "peak_pnl_pct": 60.53,
      "price_points": 298,
      "pc_5m": 0.0,
      "pc_1h": 0.0,
      "buys_1h": 0,
      "sells_1h": 0,
      "bs_ratio": 0.0,
      "completed_at": "2026-02-17T12:56:08.672345+09:00",
      "results": {
        "conservative": {
          "act": 8.0,
          "trail": 3.0,
          "sl": -15.0,
          "exit_pnl_pct": 56.78,
          "exit_pnl_usd": 11.36,
          "exit_reason": "TRAIL",
          "exit_time": "2026-02-17T12:56:08.671518+09:00",
          "highest_pnl": 60.53,
          "trail_activated": true
        },
        "current": {
          "act": 5.0,
          "trail": 3.0,
          "sl": -15.0,
          "exit_pnl_pct": 56.78,
          "exit_pnl_usd": 11.36,
          "exit_reason": "TRAIL",
          "exit_time": "2026-02-17T12:56:08.671518+09:00",
          "highest_pnl": 60.53,
          "trail_activated": true
        },
        "moderate": {
          "act": 3.0,
          "trail": 2.0,
          "sl": -15.0,
          "exit_pnl_pct": 30.06,
          "exit_pnl_usd": 6.01,
          "exit_reason": "TRAIL",
          "exit_time": "2026-02-17T12:31:54.535336+09:00",
          "highest_pnl": 32.76,
          "trail_activated": true
        },
        "tight": {
          "act": 3.0,
          "trail": 1.5,
          "sl": -15.0,
          "exit_pnl_pct": 8.97,
          "exit_pnl_usd": 1.79,
          "exit_reason": "TRAIL",
          "exit_time": "2026-02-17T12:09:26.403317+09:00",
          "highest_pnl": 10.65,
          "trail_activated": true
        },
        "aggressive": {
          "act": 2.0,
          "trail": 1.0,
          "sl": -15.0,
          "exit_pnl_pct": 0.54,
          "exit_pnl_usd": 0.11,
          "exit_reason": "TRAIL",
          "exit_time": "2026-02-17T12:00:15.730377+09:00",
          "highest_pnl": 2.22,
          "trail_activated": true
        },
        "wide_trail": {
          "act": 5.0,
          "trail": 2.0,
          "sl": -15.0,
          "exit_pnl_pct": 30.06,
          "exit_pnl_usd": 6.01,
          "exit_reason": "TRAIL",
          "exit_time": "2026-02-17T12:31:54.535336+09:00",
          "highest_pnl": 32.76,
          "trail_activated": true
        },
        "low_act": {
          "act": 2.5,
          "trail": 1.5,
          "sl": -15.0,
          "exit_pnl_pct": 8.97,
          "exit_pnl_usd": 1.79,
          "exit_reason": "TRAIL",
          "exit_time": "2026-02-17T12:09:26.403317+09:00",
          "highest_pnl": 10.65,
          "trail_activated": true
        },
        "micro": {
          "act": 1.5,
          "trail": 0.8,
          "sl": -15.0,
          "exit_pnl_pct": 0.54,
          "exit_pnl_usd": 0.11,
          "exit_reason": "TRAIL",
          "exit_time": "2026-02-17T12:00:15.730377+09:00",
          "highest_pnl": 2.22,
          "trail_activated": true
        }
      }
    },
    {
      "address": "8hhNBtcqv77soK3WfrQYdbi4ijibUExxDDfabyBnpump",
      "symbol": "watdatmean",
      "entry_time": "2026-02-17T12:47:50.250599+09:00",
      "entry_price": 1.834e-05,
      "amount_usd": 20.0,
      "score": 64.40972805525502,
      "grade": "B",
      "liquidity": 10576.38,
      "volume_24h": 57838.13,
      "token_age_min": 66.0,
      "peak_pnl_pct": 3.27,
      "price_points": 48,
      "pc_5m": 3.42,
      "pc_1h": 61.42,
      "buys_1h": 407,
      "sells_1h": 236,
      "bs_ratio": 1.72,
      "completed_at": "2026-02-17T12:56:52.343079+09:00",
      "results": {
        "conservative": {
          "act": 8.0,
          "trail": 3.0,
          "sl": -15.0,
          "exit_pnl_pct": -17.45,
          "exit_pnl_usd": -3.49,
          "exit_reason": "SL",
          "exit_time": "2026-02-17T12:56:52.342490+09:00",
          "highest_pnl": 0.0,
          "trail_activated": false
        },
        "current": {
          "act": 5.0,
          "trail": 3.0,
          "sl": -15.0,
          "exit_pnl_pct": -17.45,
          "exit_pnl_usd": -3.49,
          "exit_reason": "SL",
          "exit_time": "2026-02-17T12:56:52.342490+09:00",
          "highest_pnl": 0.0,
          "trail_activated": false
        },
        "moderate": {
          "act": 3.0,
          "trail": 2.0,
          "sl": -15.0,
          "exit_pnl_pct": -2.34,
          "exit_pnl_usd": -0.47,
          "exit_reason": "TRAIL",
          "exit_time": "2026-02-17T12:49:33.518900+09:00",
          "highest_pnl": 3.27,
          "trail_activated": true
        },
        "tight": {
          "act": 3.0,
          "trail": 1.5,
          "sl": -15.0,
          "exit_pnl_pct": -2.34,
          "exit_pnl_usd": -0.47,
          "exit_reason": "TRAIL",
          "exit_time": "2026-02-17T12:49:33.518900+09:00",
          "highest_pnl": 3.27,
          "trail_activated": true
        },
        "aggressive": {
          "act": 2.0,
          "trail": 1.0,
          "sl": -15.0,
          "exit_pnl_pct": -2.34,
          "exit_pnl_usd": -0.47,
          "exit_reason": "TRAIL",
          "exit_time": "2026-02-17T12:49:33.518900+09:00",
          "highest_pnl": 3.27,
          "trail_activated": true
        },
        "wide_trail": {
          "act": 5.0,
          "trail": 2.0,
          "sl": -15.0,
          "exit_pnl_pct": -17.45,
          "exit_pnl_usd": -3.49,
          "exit_reason": "SL",
          "exit_time": "2026-02-17T12:56:52.342490+09:00",
          "highest_pnl": 0.0,
          "trail_activated": false
        },
        "low_act": {
          "act": 2.5,
          "trail": 1.5,
          "sl": -15.0,
          "exit_pnl_pct": -2.34,
          "exit_pnl_usd": -0.47,
          "exit_reason": "TRAIL",
          "exit_time": "2026-02-17T12:49:33.518900+09:00",
          "highest_pnl": 3.27,
          "trail_activated": true
        },
        "micro": {
          "act": 1.5,
          "trail": 0.8,
          "sl": -15.0,
          "exit_pnl_pct": -2.34,
          "exit_pnl_usd": -0.47,
          "exit_reason": "TRAIL",
          "exit_time": "2026-02-17T12:49:33.518900+09:00",
          "highest_pnl": 3.27,
          "trail_activated": true
        }
      }
    },
    {
      "address": "HnYxLkQxiju5Yeoto4FNm3rgGw5MEp3NA88a1ib3398g",
      "symbol": "GUPSTER",
      "entry_time": "2026-02-17T13:19:43.718842+09:00",
      "entry_price": 7.582e-05,
      "amount_usd": 20.0,
      "score": 67.70521943032625,
      "grade": "A",
      "liquidity": 21764.11,
      "volume_24h": 138055.29,
      "token_age_min": 6.0,
      "peak_pnl_pct": 49.7,
      "price_points": 7,
      "pc_5m": 30.52,
      "pc_1h": 109.0,
      "buys_1h": 1802,
      "sells_1h": 1309,
      "bs_ratio": 1.38,
      "completed_at": "2026-02-17T13:20:52.605404+09:00",
      "results": {
        "conservative": {
          "act": 8.0,
          "trail": 3.0,
          "sl": -15.0,
          "exit_pnl_pct": 38.88,
          "exit_pnl_usd": 7.78,
          "exit_reason": "TRAIL",
          "exit_time": "2026-02-17T13:20:52.604460+09:00",
          "highest_pnl": 49.7,
          "trail_activated": true
        },
        "current": {
          "act": 5.0,
          "trail": 3.0,
          "sl": -15.0,
          "exit_pnl_pct": 38.88,
          "exit_pnl_usd": 7.78,
          "exit_reason": "TRAIL",
          "exit_time": "2026-02-17T13:20:52.604460+09:00",
          "highest_pnl": 49.7,
          "trail_activated": true
        },
        "moderate": {
          "act": 3.0,
          "trail": 2.0,
          "sl": -15.0,
          "exit_pnl_pct": 38.88,
          "exit_pnl_usd": 7.78,
          "exit_reason": "TRAIL",
          "exit_time": "2026-02-17T13:20:52.604460+09:00",
          "highest_pnl": 49.7,
          "trail_activated": true
        },
        "tight": {
          "act": 3.0,
          "trail": 1.5,
          "sl": -15.0,
          "exit_pnl_pct": 38.88,
          "exit_pnl_usd": 7.78,
          "exit_reason": "TRAIL",
          "exit_time": "2026-02-17T13:20:52.604460+09:00",
          "highest_pnl": 49.7,
          "trail_activated": true
        },
        "aggressive": {
          "act": 2.0,
          "trail": 1.0,
          "sl": -15.0,
          "exit_pnl_pct": 38.88,
          "exit_pnl_usd": 7.78,
          "exit_reason": "TRAIL",
          "exit_time": "2026-02-17T13:20:52.604460+09:00",
          "highest_pnl": 49.7,
          "trail_activated": true
        },
        "wide_trail": {
          "act": 5.0,
          "trail": 2.0,
          "sl": -15.0,
          "exit_pnl_pct": 38.88,
          "exit_pnl_usd": 7.78,
          "exit_reason": "TRAIL",
          "exit_time": "2026-02-17T13:20:52.604460+09:00",
          "highest_pnl": 49.7,
          "trail_activated": true
        },
        "low_act": {
          "act": 2.5,
          "trail": 1.5,
          "sl": -15.0,
          "exit_pnl_pct": 38.88,
          "exit_pnl_usd": 7.78,
          "exit_reason": "TRAIL",
          "exit_time": "2026-02-17T13:20:52.604460+09:00",
          "highest_pnl": 49.7,
          "trail_activated": true
        },
        "micro": {
          "act": 1.5,
          "trail": 0.8,
          "sl": -15.0,
          "exit_pnl_pct": 38.88,
          "exit_pnl_usd": 7.78,
          "exit_reason": "TRAIL",
          "exit_time": "2026-02-17T13:20:52.604460+09:00",
          "highest_pnl": 49.7,
          "trail_activated": true
        }
      }
    },
    {
      "address": "HEtD5bo9atFxRJaS9TERPLEs68uBm7i5hsG2Rmmapump",
      "symbol": "Pepe",
      "entry_time": "2026-02-17T13:26:59.533510+09:00",
      "entry_price": 6.74e-06,
      "amount_usd": 20.0,
      "score": 35.7546988199401,
      "grade": "C",
      "liquidity": 0.0,
      "volume_24h": 56693.71,
      "token_age_min": 119.1,
      "peak_pnl_pct": 3.98,
      "price_points": 10,
      "pc_5m": 0.0,
      "pc_1h": 46.55,
      "buys_1h": 0,
      "sells_1h": 0,
      "bs_ratio": 0.0,
      "completed_at": "2026-02-17T13:28:42.147045+09:00",
      "results": {
        "conservative": {
          "act": 8.0,
          "trail": 3.0,
          "sl": -15.0,
          "exit_pnl_pct": -34.42,
          "exit_pnl_usd": -6.88,
          "exit_reason": "SL",
          "exit_time": "2026-02-17T13:28:42.144960+09:00",
          "highest_pnl": 0.0,
          "trail_activated": false
        },
        "current": {
          "act": 5.0,
          "trail": 3.0,
          "sl": -15.0,
          "exit_pnl_pct": -34.42,
          "exit_pnl_usd": -6.88,
          "exit_reason": "SL",
          "exit_time": "2026-02-17T13:28:42.144960+09:00",
          "highest_pnl": 0.0,
          "trail_activated": false
        },
        "moderate": {
          "act": 3.0,
          "trail": 2.0,
          "sl": -15.0,
          "exit_pnl_pct": -7.39,
          "exit_pnl_usd": -1.48,
          "exit_reason": "TRAIL",
          "exit_time": "2026-02-17T13:28:09.798746+09:00",
          "highest_pnl": 3.98,
          "trail_activated": true
        },
        "tight": {
          "act": 3.0,
          "trail": 1.5,
          "sl": -15.0,
          "exit_pnl_pct": -7.39,
          "exit_pnl_usd": -1.48,
          "exit_reason": "TRAIL",
          "exit_time": "2026-02-17T13:28:09.798746+09:00",
          "highest_pnl": 3.98,
          "trail_activated": true
        },
        "aggressive": {
          "act": 2.0,
          "trail": 1.0,
          "sl": -15.0,
          "exit_pnl_pct": -7.39,
          "exit_pnl_usd": -1.48,
          "exit_reason": "TRAIL",
          "exit_time": "2026-02-17T13:28:09.798746+09:00",
          "highest_pnl": 3.98,
          "trail_activated": true
        },
        "wide_trail": {
          "act": 5.0,
          "trail": 2.0,
          "sl": -15.0,
          "exit_pnl_pct": -34.42,
          "exit_pnl_usd": -6.88,
          "exit_reason": "SL",
          "exit_time": "2026-02-17T13:28:42.144960+09:00",
          "highest_pnl": 0.0,
          "trail_activated": false
        },
        "low_act": {
          "act": 2.5,
          "trail": 1.5,
          "sl": -15.0,
          "exit_pnl_pct": -7.39,
          "exit_pnl_usd": -1.48,
          "exit_reason": "TRAIL",
          "exit_time": "2026-02-17T13:28:09.798746+09:00",
          "highest_pnl": 3.98,
          "trail_activated": true
        },
        "micro": {
          "act": 1.5,
          "trail": 0.8,
          "sl": -15.0,
          "exit_pnl_pct": -7.39,
          "exit_pnl_usd": -1.48,
          "exit_reason": "TRAIL",
          "exit_time": "2026-02-17T13:28:09.798746+09:00",
          "highest_pnl": 3.98,
          "trail_activated": true
        }
      }
    },
    {
      "address": "Cwo21P9vyininorHeDvvPzagjPkYcq7KbKbXfedHsend",
      "symbol": "FIREWU",
      "entry_time": "2026-02-17T13:22:55.011541+09:00",
      "entry_price": 3.35e-05,
      "amount_usd": 20.0,
      "score": 58.16713829575349,
      "grade": "B",
      "liquidity": 15479.08,
      "volume_24h": 73326.9,
      "token_age_min": 2526.0,
      "peak_pnl_pct": 37.94,
      "price_points": 35,
      "pc_5m": 2.93,
      "pc_1h": 16.1,
      "buys_1h": 20,
      "sells_1h": 8,
      "bs_ratio": 2.5,
      "completed_at": "2026-02-17T13:30:27.165981+09:00",
      "results": {
        "conservative": {
          "act": 8.0,
          "trail": 3.0,
          "sl": -15.0,
          "exit_pnl_pct": 25.28,
          "exit_pnl_usd": 5.06,
          "exit_reason": "TRAIL",
          "exit_time": "2026-02-17T13:30:27.161612+09:00",
          "highest_pnl": 37.94,
          "trail_activated": true
        },
        "current": {
          "act": 5.0,
          "trail": 3.0,
          "sl": -15.0,
          "exit_pnl_pct": 25.28,
          "exit_pnl_usd": 5.06,
          "exit_reason": "TRAIL",
          "exit_time": "2026-02-17T13:30:27.161612+09:00",
          "highest_pnl": 37.94,
          "trail_activated": true
        },
        "moderate": {
          "act": 3.0,
          "trail": 2.0,
          "sl": -15.0,
          "exit_pnl_pct": 25.28,
          "exit_pnl_usd": 5.06,
          "exit_reason": "TRAIL",
          "exit_time": "2026-02-17T13:30:27.161612+09:00",
          "highest_pnl": 37.94,
          "trail_activated": true
        },
        "tight": {
          "act": 3.0,
          "trail": 1.5,
          "sl": -15.0,
          "exit_pnl_pct": 25.28,
          "exit_pnl_usd": 5.06,
          "exit_reason": "TRAIL",
          "exit_time": "2026-02-17T13:30:27.161612+09:00",
          "highest_pnl": 37.94,
          "trail_activated": true
        },
        "aggressive": {
          "act": 2.0,
          "trail": 1.0,
          "sl": -15.0,
          "exit_pnl_pct": 25.28,
          "exit_pnl_usd": 5.06,
          "exit_reason": "TRAIL",
          "exit_time": "2026-02-17T13:30:27.161612+09:00",
          "highest_pnl": 37.94,
          "trail_activated": true
        },
        "wide_trail": {
          "act": 5.0,
          "trail": 2.0,
          "sl": -15.0,
          "exit_pnl_pct": 25.28,
          "exit_pnl_usd": 5.06,
          "exit_reason": "TRAIL",
          "exit_time": "2026-02-17T13:30:27.161612+09:00",
          "highest_pnl": 37.94,
          "trail_activated": true
        },
        "low_act": {
          "act": 2.5,
          "trail": 1.5,
          "sl": -15.0,
          "exit_pnl_pct": 25.28,
          "exit_pnl_usd": 5.06,
          "exit_reason": "TRAIL",
          "exit_time": "2026-02-17T13:30:27.161612+09:00",
          "highest_pnl": 37.94,
          "trail_activated": true
        },
        "micro": {
          "act": 1.5,
          "trail": 0.8,
          "sl": -15.0,
          "exit_pnl_pct": 25.28,
          "exit_pnl_usd": 5.06,
          "exit_reason": "TRAIL",
          "exit_time": "2026-02-17T13:30:27.161612+09:00",
          "highest_pnl": 37.94,
          "trail_activated": true
        }
      }
    },
    {
      "address": "2Jp7AkCdDYgikgbtLcrNTbU6pw6Dm5weAnEEEjwqpump",
      "symbol": "MAYA",
      "entry_time": "2026-02-17T13:26:59.533164+09:00",
      "entry_price": 0.0002513,
      "amount_usd": 20.0,
      "score": 41.01414781436077,
      "grade": "C",
      "liquidity": 40973.9,
      "volume_24h": 762310.76,
      "token_age_min": 234.0,
      "peak_pnl_pct": 13.01,
      "price_points": 19,
      "pc_5m": -20.91,
      "pc_1h": 136.0,
      "buys_1h": 1190,
      "sells_1h": 954,
      "bs_ratio": 1.25,
      "completed_at": "2026-02-17T13:30:27.166451+09:00",
      "results": {
        "conservative": {
          "act": 8.0,
          "trail": 3.0,
          "sl": -15.0,
          "exit_pnl_pct": 7.04,
          "exit_pnl_usd": 1.41,
          "exit_reason": "TRAIL",
          "exit_time": "2026-02-17T13:30:27.163590+09:00",
          "highest_pnl": 13.01,
          "trail_activated": true
        },
        "current": {
          "act": 5.0,
          "trail": 3.0,
          "sl": -15.0,
          "exit_pnl_pct": 7.04,
          "exit_pnl_usd": 1.41,
          "exit_reason": "TRAIL",
          "exit_time": "2026-02-17T13:30:27.163590+09:00",
          "highest_pnl": 13.01,
          "trail_activated": true
        },
        "moderate": {
          "act": 3.0,
          "trail": 2.0,
          "sl": -15.0,
          "exit_pnl_pct": 7.04,
          "exit_pnl_usd": 1.41,
          "exit_reason": "TRAIL",
          "exit_time": "2026-02-17T13:30:27.163590+09:00",
          "highest_pnl": 13.01,
          "trail_activated": true
        },
        "tight": {
          "act": 3.0,
          "trail": 1.5,
          "sl": -15.0,
          "exit_pnl_pct": 7.04,
          "exit_pnl_usd": 1.41,
          "exit_reason": "TRAIL",
          "exit_time": "2026-02-17T13:30:27.163590+09:00",
          "highest_pnl": 13.01,
          "trail_activated": true
        },
        "aggressive": {
          "act": 2.0,
          "trail": 1.0,
          "sl": -15.0,
          "exit_pnl_pct": 10.47,
          "exit_pnl_usd": 2.09,
          "exit_reason": "TRAIL",
          "exit_time": "2026-02-17T13:29:18.228679+09:00",
          "highest_pnl": 11.94,
          "trail_activated": true
        },
        "wide_trail": {
          "act": 5.0,
          "trail": 2.0,
          "sl": -15.0,
          "exit_pnl_pct": 7.04,
          "exit_pnl_usd": 1.41,
          "exit_reason": "TRAIL",
          "exit_time": "2026-02-17T13:30:27.163590+09:00",
          "highest_pnl": 13.01,
          "trail_activated": true
        },
        "low_act": {
          "act": 2.5,
          "trail": 1.5,
          "sl": -15.0,
          "exit_pnl_pct": 7.04,
          "exit_pnl_usd": 1.41,
          "exit_reason": "TRAIL",
          "exit_time": "2026-02-17T13:30:27.163590+09:00",
          "highest_pnl": 13.01,
          "trail_activated": true
        },
        "micro": {
          "act": 1.5,
          "trail": 0.8,
          "sl": -15.0,
          "exit_pnl_pct": 10.47,
          "exit_pnl_usd": 2.09,
          "exit_reason": "TRAIL",
          "exit_time": "2026-02-17T13:29:18.228679+09:00",
          "highest_pnl": 11.94,
          "trail_activated": true
        }
      }
    }
  ]
}