{
  "updated": "2026-02-18T10:31:18.384069+09:00",
  "total_completed": 19,
  "total_open": 10,
  "today_entries": 29,
  "param_summary": {
    "live": {
      "params": {
        "act": 5.0,
        "trail": 2.0,
        "sl": -10.0
      },
      "trades": 19,
      "win_rate": 10.5,
      "avg_pnl_pct": -8.83,
      "total_pnl_pct": -167.79,
      "total_pnl_usd": -33.56,
      "best_trade": 28.06,
      "worst_trade": -62.2,
      "reasons": {
        "SL": 12,
        "TRAIL": 5,
        "TIMEOUT": 2
      }
    },
    "conservative": {
      "params": {
        "act": 8.0,
        "trail": 3.0,
        "sl": -10.0
      },
      "trades": 19,
      "win_rate": 15.8,
      "avg_pnl_pct": -9.9,
      "total_pnl_pct": -188.16,
      "total_pnl_usd": -37.63,
      "best_trade": 25.16,
      "worst_trade": -62.2,
      "reasons": {
        "SL": 14,
        "TRAIL": 3,
        "TIMEOUT": 2
      }
    },
    "current": {
      "params": {
        "act": 5.0,
        "trail": 3.0,
        "sl": -10.0
      },
      "trades": 19,
      "win_rate": 10.5,
      "avg_pnl_pct": -9.05,
      "total_pnl_pct": -171.96,
      "total_pnl_usd": -34.39,
      "best_trade": 25.16,
      "worst_trade": -62.2,
      "reasons": {
        "SL": 12,
        "TRAIL": 5,
        "TIMEOUT": 2
      }
    },
    "moderate": {
      "params": {
        "act": 3.0,
        "trail": 2.0,
        "sl": -10.0
      },
      "trades": 19,
      "win_rate": 15.8,
      "avg_pnl_pct": -8.74,
      "total_pnl_pct": -166.02,
      "total_pnl_usd": -33.2,
      "best_trade": 28.06,
      "worst_trade": -62.2,
      "reasons": {
        "SL": 12,
        "TRAIL": 6,
        "TIMEOUT": 1
      }
    },
    "tight": {
      "params": {
        "act": 3.0,
        "trail": 1.5,
        "sl": -10.0
      },
      "trades": 19,
      "win_rate": 15.8,
      "avg_pnl_pct": -8.72,
      "total_pnl_pct": -165.65,
      "total_pnl_usd": -33.13,
      "best_trade": 28.72,
      "worst_trade": -62.2,
      "reasons": {
        "SL": 12,
        "TRAIL": 6,
        "TIMEOUT": 1
      }
    },
    "aggressive": {
      "params": {
        "act": 2.0,
        "trail": 1.0,
        "sl": -10.0
      },
      "trades": 19,
      "win_rate": 21.1,
      "avg_pnl_pct": -4.41,
      "total_pnl_pct": -83.88,
      "total_pnl_usd": -16.78,
      "best_trade": 47.57,
      "worst_trade": -17.29,
      "reasons": {
        "SL": 11,
        "TRAIL": 7,
        "TIMEOUT": 1
      }
    },
    "wide_trail": {
      "params": {
        "act": 5.0,
        "trail": 2.0,
        "sl": -15.0
      },
      "trades": 19,
      "win_rate": 15.8,
      "avg_pnl_pct": -9.43,
      "total_pnl_pct": -179.16,
      "total_pnl_usd": -35.83,
      "best_trade": 28.06,
      "worst_trade": -62.2,
      "reasons": {
        "SL": 8,
        "TRAIL": 7,
        "TIMEOUT": 4
      }
    },
    "wide_sl15": {
      "params": {
        "act": 5.0,
        "trail": 3.0,
        "sl": -15.0
      },
      "trades": 19,
      "win_rate": 15.8,
      "avg_pnl_pct": -9.52,
      "total_pnl_pct": -180.79,
      "total_pnl_usd": -36.16,
      "best_trade": 25.16,
      "worst_trade": -62.2,
      "reasons": {
        "SL": 8,
        "TRAIL": 7,
        "TIMEOUT": 4
      }
    }
  },
  "filter_summary": {
    "live": {
      "config": {
        "min_liq": 28500,
        "min_score": 37.5,
        "min_buys": 0,
        "min_bs_ratio": 1.0
      },
      "trades": 17,
      "current_wr": 11.8,
      "current_avg": -8.4,
      "momentum_wr": 17.6,
      "momentum_avg": -10.27
    }
  },
  "open_positions": [
    {
      "symbol": "DOG",
      "entry_time": "2026-02-18T08:52:59.649635+09:00",
      "entry_price": 0.0009708799999999999,
      "current_pnl_pct": -5.77,
      "peak_pnl_pct": 0.0,
      "price_points": 395,
      "active_params": [
        "live",
        "conservative",
        "current",
        "moderate",
        "tight",
        "aggressive",
        "wide_trail",
        "wide_sl15"
      ],
      "score": 38.856830121874495,
      "grade": "C"
    },
    {
      "symbol": "BRETTA",
      "entry_time": "2026-02-18T08:56:14.248330+09:00",
      "entry_price": 0.00016092499999999997,
      "current_pnl_pct": -0.21,
      "peak_pnl_pct": 1.7865465278856796,
      "price_points": 380,
      "active_params": [
        "live",
        "conservative",
        "current",
        "moderate",
        "tight",
        "aggressive",
        "wide_trail",
        "wide_sl15"
      ],
      "score": 47.52844968846641,
      "grade": "C"
    },
    {
      "symbol": "Pigeon",
      "entry_time": "2026-02-18T09:01:37.162037+09:00",
      "entry_price": 0.00035065249999999997,
      "current_pnl_pct": -1.85,
      "peak_pnl_pct": 0.0,
      "price_points": 355,
      "active_params": [
        "wide_trail",
        "wide_sl15"
      ],
      "score": 39.04831478948587,
      "grade": "C"
    },
    {
      "symbol": "PEPE",
      "entry_time": "2026-02-18T09:07:02.031342+09:00",
      "entry_price": 0.00014852249999999998,
      "current_pnl_pct": -4.29,
      "peak_pnl_pct": 0.0,
      "price_points": 330,
      "active_params": [
        "live",
        "conservative",
        "current",
        "moderate",
        "tight",
        "aggressive",
        "wide_trail",
        "wide_sl15"
      ],
      "score": 49.06540860234861,
      "grade": "C"
    },
    {
      "symbol": "DOG",
      "entry_time": "2026-02-18T09:14:39.480953+09:00",
      "entry_price": 0.0005488874999999999,
      "current_pnl_pct": -6.07,
      "peak_pnl_pct": 0.0,
      "price_points": 295,
      "active_params": [
        "live",
        "conservative",
        "current",
        "moderate",
        "tight",
        "aggressive",
        "wide_trail",
        "wide_sl15"
      ],
      "score": 37.648371511308476,
      "grade": "C"
    },
    {
      "symbol": "GAS",
      "entry_time": "2026-02-18T09:30:45.850078+09:00",
      "entry_price": 3.6622412549858156e-05,
      "current_pnl_pct": -4.66,
      "peak_pnl_pct": 0.0,
      "price_points": 235,
      "active_params": [
        "live",
        "conservative",
        "current",
        "moderate",
        "tight",
        "aggressive",
        "wide_trail",
        "wide_sl15"
      ],
      "score": 50.21585266903129,
      "grade": "B"
    },
    {
      "symbol": "67",
      "entry_time": "2026-02-18T09:35:23.744678+09:00",
      "entry_price": 0.0025655749999999996,
      "current_pnl_pct": -8.68,
      "peak_pnl_pct": 0.0,
      "price_points": 217,
      "active_params": [
        "wide_trail",
        "wide_sl15"
      ],
      "score": 39.9219314174641,
      "grade": "C"
    },
    {
      "symbol": "丙午",
      "entry_time": "2026-02-18T09:59:24.383492+09:00",
      "entry_price": 0.0004490525,
      "current_pnl_pct": -11.44,
      "peak_pnl_pct": 0.0,
      "price_points": 121,
      "active_params": [
        "wide_trail",
        "wide_sl15"
      ],
      "score": 40.01821805490908,
      "grade": "C"
    },
    {
      "symbol": "CAT",
      "entry_time": "2026-02-18T10:01:42.887780+09:00",
      "entry_price": 0.0030729499999999996,
      "current_pnl_pct": -6.02,
      "peak_pnl_pct": 0.0,
      "price_points": 114,
      "active_params": [
        "live",
        "conservative",
        "current",
        "moderate",
        "tight",
        "aggressive",
        "wide_trail",
        "wide_sl15"
      ],
      "score": 39.62111145936682,
      "grade": "C"
    },
    {
      "symbol": "CHIMP",
      "entry_time": "2026-02-18T10:12:53.395974+09:00",
      "entry_price": 3.6622412549858156e-05,
      "current_pnl_pct": -4.66,
      "peak_pnl_pct": 0.0,
      "price_points": 68,
      "active_params": [
        "live",
        "conservative",
        "current",
        "moderate",
        "tight",
        "aggressive",
        "wide_trail",
        "wide_sl15"
      ],
      "score": 67.85250666987602,
      "grade": "A"
    }
  ],
  "recent_completed": [
    {
      "address": "412zDygnwP9DzitnQVgRKUFFTDmrYScFch6P2k39pump",
      "symbol": "Jellybean",
      "entry_time": "2026-02-18T08:26:50.406485+09:00",
      "entry_price": 0.00015549249999999998,
      "amount_usd": 20.0,
      "score": 66.16856190592381,
      "grade": "A",
      "liquidity": 34610.64,
      "volume_24h": 94828.76,
      "token_age_min": 8982.0,
      "peak_pnl_pct": 0.2,
      "price_points": 34,
      "pc_5m": 2.04,
      "pc_1h": 54.12,
      "buys_1h": 160,
      "sells_1h": 98,
      "bs_ratio": 1.63,
      "completed_at": "2026-02-18T08:33:52.676513+09:00",
      "results": {
        "live": {
          "act": 5.0,
          "trail": 2.0,
          "sl": -10.0,
          "exit_pnl_pct": -10.4,
          "exit_pnl_usd": -2.08,
          "exit_reason": "SL",
          "exit_time": "2026-02-18T08:30:39.297708+09:00",
          "highest_pnl": 0.0,
          "trail_activated": false
        },
        "conservative": {
          "act": 8.0,
          "trail": 3.0,
          "sl": -10.0,
          "exit_pnl_pct": -10.4,
          "exit_pnl_usd": -2.08,
          "exit_reason": "SL",
          "exit_time": "2026-02-18T08:30:39.297708+09:00",
          "highest_pnl": 0.0,
          "trail_activated": false
        },
        "current": {
          "act": 5.0,
          "trail": 3.0,
          "sl": -10.0,
          "exit_pnl_pct": -10.4,
          "exit_pnl_usd": -2.08,
          "exit_reason": "SL",
          "exit_time": "2026-02-18T08:30:39.297708+09:00",
          "highest_pnl": 0.0,
          "trail_activated": false
        },
        "moderate": {
          "act": 3.0,
          "trail": 2.0,
          "sl": -10.0,
          "exit_pnl_pct": -10.4,
          "exit_pnl_usd": -2.08,
          "exit_reason": "SL",
          "exit_time": "2026-02-18T08:30:39.297708+09:00",
          "highest_pnl": 0.0,
          "trail_activated": false
        },
        "tight": {
          "act": 3.0,
          "trail": 1.5,
          "sl": -10.0,
          "exit_pnl_pct": -10.4,
          "exit_pnl_usd": -2.08,
          "exit_reason": "SL",
          "exit_time": "2026-02-18T08:30:39.297708+09:00",
          "highest_pnl": 0.0,
          "trail_activated": false
        },
        "aggressive": {
          "act": 2.0,
          "trail": 1.0,
          "sl": -10.0,
          "exit_pnl_pct": -10.4,
          "exit_pnl_usd": -2.08,
          "exit_reason": "SL",
          "exit_time": "2026-02-18T08:30:39.297708+09:00",
          "highest_pnl": 0.0,
          "trail_activated": false
        },
        "wide_trail": {
          "act": 5.0,
          "trail": 2.0,
          "sl": -15.0,
          "exit_pnl_pct": -16.79,
          "exit_pnl_usd": -3.36,
          "exit_reason": "SL",
          "exit_time": "2026-02-18T08:33:52.673374+09:00",
          "highest_pnl": 0.0,
          "trail_activated": false
        },
        "wide_sl15": {
          "act": 5.0,
          "trail": 3.0,
          "sl": -15.0,
          "exit_pnl_pct": -16.79,
          "exit_pnl_usd": -3.36,
          "exit_reason": "SL",
          "exit_time": "2026-02-18T08:33:52.673374+09:00",
          "highest_pnl": 0.0,
          "trail_activated": false
        }
      },
      "momentum_exit": {
        "param_used": "aggressive",
        "buys_1h": 160,
        "exit_pnl_pct": -10.4,
        "exit_pnl_usd": -2.08,
        "exit_reason": "SL"
      },
      "filter_match": {
        "live": true
      }
    },
    {
      "address": "Gv5SW3JJam65NURPf8ViTrek14JghccjZRA3ypid6vbN",
      "symbol": "Jwan",
      "entry_time": "2026-02-18T08:37:38.240483+09:00",
      "entry_price": 0.00017332749999999998,
      "amount_usd": 20.0,
      "score": 70.19696908725845,
      "grade": "A",
      "liquidity": 32178.18,
      "volume_24h": 235596.56,
      "token_age_min": 48.0,
      "peak_pnl_pct": 18.35,
      "price_points": 9,
      "pc_5m": 121.0,
      "pc_1h": 372.0,
      "buys_1h": 2579,
      "sells_1h": 1841,
      "bs_ratio": 1.4,
      "completed_at": "2026-02-18T08:39:16.229628+09:00",
      "results": {
        "live": {
          "act": 5.0,
          "trail": 2.0,
          "sl": -10.0,
          "exit_pnl_pct": -3.7,
          "exit_pnl_usd": -0.74,
          "exit_reason": "TRAIL",
          "exit_time": "2026-02-18T08:38:11.560352+09:00",
          "highest_pnl": 7.5,
          "trail_activated": true
        },
        "conservative": {
          "act": 8.0,
          "trail": 3.0,
          "sl": -10.0,
          "exit_pnl_pct": 8.06,
          "exit_pnl_usd": 1.61,
          "exit_reason": "TRAIL",
          "exit_time": "2026-02-18T08:39:16.229320+09:00",
          "highest_pnl": 18.35,
          "trail_activated": true
        },
        "current": {
          "act": 5.0,
          "trail": 3.0,
          "sl": -10.0,
          "exit_pnl_pct": -3.7,
          "exit_pnl_usd": -0.74,
          "exit_reason": "TRAIL",
          "exit_time": "2026-02-18T08:38:11.560352+09:00",
          "highest_pnl": 7.5,
          "trail_activated": true
        },
        "moderate": {
          "act": 3.0,
          "trail": 2.0,
          "sl": -10.0,
          "exit_pnl_pct": -3.7,
          "exit_pnl_usd": -0.74,
          "exit_reason": "TRAIL",
          "exit_time": "2026-02-18T08:38:11.560352+09:00",
          "highest_pnl": 7.5,
          "trail_activated": true
        },
        "tight": {
          "act": 3.0,
          "trail": 1.5,
          "sl": -10.0,
          "exit_pnl_pct": -3.7,
          "exit_pnl_usd": -0.74,
          "exit_reason": "TRAIL",
          "exit_time": "2026-02-18T08:38:11.560352+09:00",
          "highest_pnl": 7.5,
          "trail_activated": true
        },
        "aggressive": {
          "act": 2.0,
          "trail": 1.0,
          "sl": -10.0,
          "exit_pnl_pct": -3.7,
          "exit_pnl_usd": -0.74,
          "exit_reason": "TRAIL",
          "exit_time": "2026-02-18T08:38:11.560352+09:00",
          "highest_pnl": 7.5,
          "trail_activated": true
        },
        "wide_trail": {
          "act": 5.0,
          "trail": 2.0,
          "sl": -15.0,
          "exit_pnl_pct": -3.7,
          "exit_pnl_usd": -0.74,
          "exit_reason": "TRAIL",
          "exit_time": "2026-02-18T08:38:11.560352+09:00",
          "highest_pnl": 7.5,
          "trail_activated": true
        },
        "wide_sl15": {
          "act": 5.0,
          "trail": 3.0,
          "sl": -15.0,
          "exit_pnl_pct": -3.7,
          "exit_pnl_usd": -0.74,
          "exit_reason": "TRAIL",
          "exit_time": "2026-02-18T08:38:11.560352+09:00",
          "highest_pnl": 7.5,
          "trail_activated": true
        }
      },
      "momentum_exit": {
        "param_used": "current",
        "buys_1h": 2579,
        "exit_pnl_pct": -3.7,
        "exit_pnl_usd": -0.74,
        "exit_reason": "TRAIL"
      },
      "filter_match": {
        "live": true
      }
    },
    {
      "address": "Hkqt9pm7zJMA9oCQttVM35wG7cZwgQieCZKcNaKcpump",
      "symbol": "DEVLESS",
      "entry_time": "2026-02-18T08:45:19.267557+09:00",
      "entry_price": 0.0001325325,
      "amount_usd": 20.0,
      "score": 57.537782725986816,
      "grade": "B",
      "liquidity": 29074.99,
      "volume_24h": 585972.54,
      "token_age_min": 468.0,
      "peak_pnl_pct": 0.0,
      "price_points": 26,
      "pc_5m": 25.46,
      "pc_1h": 39.93,
      "buys_1h": 594,
      "sells_1h": 324,
      "bs_ratio": 1.83,
      "completed_at": "2026-02-18T08:50:49.604054+09:00",
      "results": {
        "live": {
          "act": 5.0,
          "trail": 2.0,
          "sl": -10.0,
          "exit_pnl_pct": -10.69,
          "exit_pnl_usd": -2.14,
          "exit_reason": "SL",
          "exit_time": "2026-02-18T08:50:17.343708+09:00",
          "highest_pnl": 0.0,
          "trail_activated": false
        },
        "conservative": {
          "act": 8.0,
          "trail": 3.0,
          "sl": -10.0,
          "exit_pnl_pct": -10.69,
          "exit_pnl_usd": -2.14,
          "exit_reason": "SL",
          "exit_time": "2026-02-18T08:50:17.343708+09:00",
          "highest_pnl": 0.0,
          "trail_activated": false
        },
        "current": {
          "act": 5.0,
          "trail": 3.0,
          "sl": -10.0,
          "exit_pnl_pct": -10.69,
          "exit_pnl_usd": -2.14,
          "exit_reason": "SL",
          "exit_time": "2026-02-18T08:50:17.343708+09:00",
          "highest_pnl": 0.0,
          "trail_activated": false
        },
        "moderate": {
          "act": 3.0,
          "trail": 2.0,
          "sl": -10.0,
          "exit_pnl_pct": -10.69,
          "exit_pnl_usd": -2.14,
          "exit_reason": "SL",
          "exit_time": "2026-02-18T08:50:17.343708+09:00",
          "highest_pnl": 0.0,
          "trail_activated": false
        },
        "tight": {
          "act": 3.0,
          "trail": 1.5,
          "sl": -10.0,
          "exit_pnl_pct": -10.69,
          "exit_pnl_usd": -2.14,
          "exit_reason": "SL",
          "exit_time": "2026-02-18T08:50:17.343708+09:00",
          "highest_pnl": 0.0,
          "trail_activated": false
        },
        "aggressive": {
          "act": 2.0,
          "trail": 1.0,
          "sl": -10.0,
          "exit_pnl_pct": -10.69,
          "exit_pnl_usd": -2.14,
          "exit_reason": "SL",
          "exit_time": "2026-02-18T08:50:17.343708+09:00",
          "highest_pnl": 0.0,
          "trail_activated": false
        },
        "wide_trail": {
          "act": 5.0,
          "trail": 2.0,
          "sl": -15.0,
          "exit_pnl_pct": -15.77,
          "exit_pnl_usd": -3.15,
          "exit_reason": "SL",
          "exit_time": "2026-02-18T08:50:49.603398+09:00",
          "highest_pnl": 0.0,
          "trail_activated": false
        },
        "wide_sl15": {
          "act": 5.0,
          "trail": 3.0,
          "sl": -15.0,
          "exit_pnl_pct": -15.77,
          "exit_pnl_usd": -3.15,
          "exit_reason": "SL",
          "exit_time": "2026-02-18T08:50:49.603398+09:00",
          "highest_pnl": 0.0,
          "trail_activated": false
        }
      },
      "momentum_exit": {
        "param_used": "aggressive",
        "buys_1h": 594,
        "exit_pnl_pct": -10.69,
        "exit_pnl_usd": -2.14,
        "exit_reason": "SL"
      },
      "filter_match": {
        "live": true
      }
    },
    {
      "address": "Bf8YoLZNY42yc3MAgCrvFwSuM1RH8EwefgvRAqLppump",
      "symbol": "IF",
      "entry_time": "2026-02-18T08:26:50.410067+09:00",
      "entry_price": 0.00032133749999999994,
      "amount_usd": 20.0,
      "score": 47.106334325109344,
      "grade": "C",
      "liquidity": 50541.66,
      "volume_24h": 3063561.07,
      "token_age_min": 1134.0,
      "peak_pnl_pct": 2.89,
      "price_points": 182,
      "pc_5m": 1.05,
      "pc_1h": 13.79,
      "buys_1h": 547,
      "sells_1h": 476,
      "bs_ratio": 1.15,
      "completed_at": "2026-02-18T09:06:08.870603+09:00",
      "results": {
        "live": {
          "act": 5.0,
          "trail": 2.0,
          "sl": -10.0,
          "exit_pnl_pct": -11.01,
          "exit_pnl_usd": -2.2,
          "exit_reason": "SL",
          "exit_time": "2026-02-18T08:31:12.133669+09:00",
          "highest_pnl": 0.0,
          "trail_activated": false
        },
        "conservative": {
          "act": 8.0,
          "trail": 3.0,
          "sl": -10.0,
          "exit_pnl_pct": -11.01,
          "exit_pnl_usd": -2.2,
          "exit_reason": "SL",
          "exit_time": "2026-02-18T08:31:12.133669+09:00",
          "highest_pnl": 0.0,
          "trail_activated": false
        },
        "current": {
          "act": 5.0,
          "trail": 3.0,
          "sl": -10.0,
          "exit_pnl_pct": -11.01,
          "exit_pnl_usd": -2.2,
          "exit_reason": "SL",
          "exit_time": "2026-02-18T08:31:12.133669+09:00",
          "highest_pnl": 0.0,
          "trail_activated": false
        },
        "moderate": {
          "act": 3.0,
          "trail": 2.0,
          "sl": -10.0,
          "exit_pnl_pct": -11.01,
          "exit_pnl_usd": -2.2,
          "exit_reason": "SL",
          "exit_time": "2026-02-18T08:31:12.133669+09:00",
          "highest_pnl": 0.0,
          "trail_activated": false
        },
        "tight": {
          "act": 3.0,
          "trail": 1.5,
          "sl": -10.0,
          "exit_pnl_pct": -11.01,
          "exit_pnl_usd": -2.2,
          "exit_reason": "SL",
          "exit_time": "2026-02-18T08:31:12.133669+09:00",
          "highest_pnl": 0.0,
          "trail_activated": false
        },
        "aggressive": {
          "act": 2.0,
          "trail": 1.0,
          "sl": -10.0,
          "exit_pnl_pct": -11.01,
          "exit_pnl_usd": -2.2,
          "exit_reason": "SL",
          "exit_time": "2026-02-18T08:31:12.133669+09:00",
          "highest_pnl": 0.0,
          "trail_activated": false
        },
        "wide_trail": {
          "act": 5.0,
          "trail": 2.0,
          "sl": -15.0,
          "exit_pnl_pct": -19.53,
          "exit_pnl_usd": -3.91,
          "exit_reason": "SL",
          "exit_time": "2026-02-18T09:06:08.868398+09:00",
          "highest_pnl": 0.0,
          "trail_activated": false
        },
        "wide_sl15": {
          "act": 5.0,
          "trail": 3.0,
          "sl": -15.0,
          "exit_pnl_pct": -19.53,
          "exit_pnl_usd": -3.91,
          "exit_reason": "SL",
          "exit_time": "2026-02-18T09:06:08.868398+09:00",
          "highest_pnl": 0.0,
          "trail_activated": false
        }
      },
      "momentum_exit": {
        "param_used": "aggressive",
        "buys_1h": 547,
        "exit_pnl_pct": -11.01,
        "exit_pnl_usd": -2.2,
        "exit_reason": "SL"
      },
      "filter_match": {
        "live": true
      }
    },
    {
      "address": "DAM9FkN7nzYaFR9igsZLHi6jBnqNVqpqYikNDGZDpump",
      "symbol": "GOBAMA",
      "entry_time": "2026-02-18T08:26:50.408605+09:00",
      "entry_price": 0.004420825,
      "amount_usd": 20.0,
      "score": 53.09153438841858,
      "grade": "B",
      "liquidity": 161471.52,
      "volume_24h": 298678.38,
      "token_age_min": 72.0,
      "peak_pnl_pct": 104.62,
      "price_points": 194,
      "pc_5m": 7.68,
      "pc_1h": 31.93,
      "buys_1h": 3231,
      "sells_1h": 2463,
      "bs_ratio": 1.31,
      "completed_at": "2026-02-18T09:08:40.003235+09:00",
      "results": {
        "live": {
          "act": 5.0,
          "trail": 2.0,
          "sl": -10.0,
          "exit_pnl_pct": -62.2,
          "exit_pnl_usd": -12.44,
          "exit_reason": "SL",
          "exit_time": "2026-02-18T09:08:40.000274+09:00",
          "highest_pnl": 104.62,
          "trail_activated": true
        },
        "conservative": {
          "act": 8.0,
          "trail": 3.0,
          "sl": -10.0,
          "exit_pnl_pct": -62.2,
          "exit_pnl_usd": -12.44,
          "exit_reason": "SL",
          "exit_time": "2026-02-18T09:08:40.000274+09:00",
          "highest_pnl": 104.62,
          "trail_activated": true
        },
        "current": {
          "act": 5.0,
          "trail": 3.0,
          "sl": -10.0,
          "exit_pnl_pct": -62.2,
          "exit_pnl_usd": -12.44,
          "exit_reason": "SL",
          "exit_time": "2026-02-18T09:08:40.000274+09:00",
          "highest_pnl": 104.62,
          "trail_activated": true
        },
        "moderate": {
          "act": 3.0,
          "trail": 2.0,
          "sl": -10.0,
          "exit_pnl_pct": -62.2,
          "exit_pnl_usd": -12.44,
          "exit_reason": "SL",
          "exit_time": "2026-02-18T09:08:40.000274+09:00",
          "highest_pnl": 104.62,
          "trail_activated": true
        },
        "tight": {
          "act": 3.0,
          "trail": 1.5,
          "sl": -10.0,
          "exit_pnl_pct": -62.2,
          "exit_pnl_usd": -12.44,
          "exit_reason": "SL",
          "exit_time": "2026-02-18T09:08:40.000274+09:00",
          "highest_pnl": 104.62,
          "trail_activated": true
        },
        "aggressive": {
          "act": 2.0,
          "trail": 1.0,
          "sl": -10.0,
          "exit_pnl_pct": 47.57,
          "exit_pnl_usd": 9.51,
          "exit_reason": "TRAIL",
          "exit_time": "2026-02-18T08:57:18.934829+09:00",
          "highest_pnl": 48.8,
          "trail_activated": true
        },
        "wide_trail": {
          "act": 5.0,
          "trail": 2.0,
          "sl": -15.0,
          "exit_pnl_pct": -62.2,
          "exit_pnl_usd": -12.44,
          "exit_reason": "SL",
          "exit_time": "2026-02-18T09:08:40.000274+09:00",
          "highest_pnl": 104.62,
          "trail_activated": true
        },
        "wide_sl15": {
          "act": 5.0,
          "trail": 3.0,
          "sl": -15.0,
          "exit_pnl_pct": -62.2,
          "exit_pnl_usd": -12.44,
          "exit_reason": "SL",
          "exit_time": "2026-02-18T09:08:40.000274+09:00",
          "highest_pnl": 104.62,
          "trail_activated": true
        }
      },
      "momentum_exit": {
        "param_used": "current",
        "buys_1h": 3231,
        "exit_pnl_pct": -62.2,
        "exit_pnl_usd": -12.44,
        "exit_reason": "SL"
      },
      "filter_match": {
        "live": true
      }
    },
    {
      "address": "8naeAc6qBpZmesBtJB34TwX55MhVR8bBUMs4JayUpump",
      "symbol": "TANDEM",
      "entry_time": "2026-02-18T09:14:39.479495+09:00",
      "entry_price": 0.00022344999999999998,
      "amount_usd": 20.0,
      "score": 45.48647621154556,
      "grade": "C",
      "liquidity": 37429.54,
      "volume_24h": 419759.92,
      "token_age_min": 96.0,
      "peak_pnl_pct": 0.0,
      "price_points": 6,
      "pc_5m": 26.81,
      "pc_1h": 22.15,
      "buys_1h": 426,
      "sells_1h": 577,
      "bs_ratio": 0.74,
      "completed_at": "2026-02-18T09:15:45.208086+09:00",
      "results": {
        "live": {
          "act": 5.0,
          "trail": 2.0,
          "sl": -10.0,
          "exit_pnl_pct": -11.95,
          "exit_pnl_usd": -2.39,
          "exit_reason": "SL",
          "exit_time": "2026-02-18T09:15:12.616919+09:00",
          "highest_pnl": 0.0,
          "trail_activated": false
        },
        "conservative": {
          "act": 8.0,
          "trail": 3.0,
          "sl": -10.0,
          "exit_pnl_pct": -11.95,
          "exit_pnl_usd": -2.39,
          "exit_reason": "SL",
          "exit_time": "2026-02-18T09:15:12.616919+09:00",
          "highest_pnl": 0.0,
          "trail_activated": false
        },
        "current": {
          "act": 5.0,
          "trail": 3.0,
          "sl": -10.0,
          "exit_pnl_pct": -11.95,
          "exit_pnl_usd": -2.39,
          "exit_reason": "SL",
          "exit_time": "2026-02-18T09:15:12.616919+09:00",
          "highest_pnl": 0.0,
          "trail_activated": false
        },
        "moderate": {
          "act": 3.0,
          "trail": 2.0,
          "sl": -10.0,
          "exit_pnl_pct": -11.95,
          "exit_pnl_usd": -2.39,
          "exit_reason": "SL",
          "exit_time": "2026-02-18T09:15:12.616919+09:00",
          "highest_pnl": 0.0,
          "trail_activated": false
        },
        "tight": {
          "act": 3.0,
          "trail": 1.5,
          "sl": -10.0,
          "exit_pnl_pct": -11.95,
          "exit_pnl_usd": -2.39,
          "exit_reason": "SL",
          "exit_time": "2026-02-18T09:15:12.616919+09:00",
          "highest_pnl": 0.0,
          "trail_activated": false
        },
        "aggressive": {
          "act": 2.0,
          "trail": 1.0,
          "sl": -10.0,
          "exit_pnl_pct": -11.95,
          "exit_pnl_usd": -2.39,
          "exit_reason": "SL",
          "exit_time": "2026-02-18T09:15:12.616919+09:00",
          "highest_pnl": 0.0,
          "trail_activated": false
        },
        "wide_trail": {
          "act": 5.0,
          "trail": 2.0,
          "sl": -15.0,
          "exit_pnl_pct": -17.36,
          "exit_pnl_usd": -3.47,
          "exit_reason": "SL",
          "exit_time": "2026-02-18T09:15:45.207436+09:00",
          "highest_pnl": 0.0,
          "trail_activated": false
        },
        "wide_sl15": {
          "act": 5.0,
          "trail": 3.0,
          "sl": -15.0,
          "exit_pnl_pct": -17.36,
          "exit_pnl_usd": -3.47,
          "exit_reason": "SL",
          "exit_time": "2026-02-18T09:15:45.207436+09:00",
          "highest_pnl": 0.0,
          "trail_activated": false
        }
      },
      "momentum_exit": {
        "param_used": "aggressive",
        "buys_1h": 426,
        "exit_pnl_pct": -11.95,
        "exit_pnl_usd": -2.39,
        "exit_reason": "SL"
      },
      "filter_match": {
        "live": false
      }
    },
    {
      "address": "jk1T35eWK41MBMM8AWoYVaNbjHEEQzMDetTsfnqpump",
      "symbol": "SOL",
      "entry_time": "2026-02-18T08:51:54.072204+09:00",
      "entry_price": 0.002174025,
      "amount_usd": 20.0,
      "score": 48.66443656832587,
      "grade": "C",
      "liquidity": 205861.85,
      "volume_24h": 222030.53,
      "token_age_min": 72139.4,
      "peak_pnl_pct": 0.0,
      "price_points": 120,
      "pc_5m": 0.5,
      "pc_1h": 0.91,
      "buys_1h": 24,
      "sells_1h": 11,
      "bs_ratio": 0.0,
      "completed_at": "2026-02-18T09:17:33.683735+09:00",
      "results": {
        "live": {
          "act": 5.0,
          "trail": 2.0,
          "sl": -10.0,
          "exit_pnl_pct": -13.22,
          "exit_pnl_usd": -2.64,
          "exit_reason": "SL",
          "exit_time": "2026-02-18T09:17:01.306721+09:00",
          "highest_pnl": 0.0,
          "trail_activated": false
        },
        "conservative": {
          "act": 8.0,
          "trail": 3.0,
          "sl": -10.0,
          "exit_pnl_pct": -13.22,
          "exit_pnl_usd": -2.64,
          "exit_reason": "SL",
          "exit_time": "2026-02-18T09:17:01.306721+09:00",
          "highest_pnl": 0.0,
          "trail_activated": false
        },
        "current": {
          "act": 5.0,
          "trail": 3.0,
          "sl": -10.0,
          "exit_pnl_pct": -13.22,
          "exit_pnl_usd": -2.64,
          "exit_reason": "SL",
          "exit_time": "2026-02-18T09:17:01.306721+09:00",
          "highest_pnl": 0.0,
          "trail_activated": false
        },
        "moderate": {
          "act": 3.0,
          "trail": 2.0,
          "sl": -10.0,
          "exit_pnl_pct": -13.22,
          "exit_pnl_usd": -2.64,
          "exit_reason": "SL",
          "exit_time": "2026-02-18T09:17:01.306721+09:00",
          "highest_pnl": 0.0,
          "trail_activated": false
        },
        "tight": {
          "act": 3.0,
          "trail": 1.5,
          "sl": -10.0,
          "exit_pnl_pct": -13.22,
          "exit_pnl_usd": -2.64,
          "exit_reason": "SL",
          "exit_time": "2026-02-18T09:17:01.306721+09:00",
          "highest_pnl": 0.0,
          "trail_activated": false
        },
        "aggressive": {
          "act": 2.0,
          "trail": 1.0,
          "sl": -10.0,
          "exit_pnl_pct": -13.22,
          "exit_pnl_usd": -2.64,
          "exit_reason": "SL",
          "exit_time": "2026-02-18T09:17:01.306721+09:00",
          "highest_pnl": 0.0,
          "trail_activated": false
        },
        "wide_trail": {
          "act": 5.0,
          "trail": 2.0,
          "sl": -15.0,
          "exit_pnl_pct": -15.46,
          "exit_pnl_usd": -3.09,
          "exit_reason": "SL",
          "exit_time": "2026-02-18T09:17:33.681151+09:00",
          "highest_pnl": 0.0,
          "trail_activated": false
        },
        "wide_sl15": {
          "act": 5.0,
          "trail": 3.0,
          "sl": -15.0,
          "exit_pnl_pct": -15.46,
          "exit_pnl_usd": -3.09,
          "exit_reason": "SL",
          "exit_time": "2026-02-18T09:17:33.681151+09:00",
          "highest_pnl": 0.0,
          "trail_activated": false
        }
      },
      "momentum_exit": {
        "param_used": "conservative",
        "buys_1h": 24,
        "exit_pnl_pct": -13.22,
        "exit_pnl_usd": -2.64,
        "exit_reason": "SL"
      },
      "filter_match": {
        "live": true
      }
    },
    {
      "address": "DPbVGNrTTeSLWG9yJ2vjHb424fSrsp8MJ8wHPritpump",
      "symbol": "WAGMI",
      "entry_time": "2026-02-18T09:14:39.478446+09:00",
      "entry_price": 0.00014985499999999998,
      "amount_usd": 20.0,
      "score": 70.7532624129542,
      "grade": "A",
      "liquidity": 30811.32,
      "volume_24h": 449313.91,
      "token_age_min": 48.0,
      "peak_pnl_pct": 14.51,
      "price_points": 15,
      "pc_5m": 21.86,
      "pc_1h": 308.0,
      "buys_1h": 4487,
      "sells_1h": 3089,
      "bs_ratio": 1.45,
      "completed_at": "2026-02-18T09:17:33.684394+09:00",
      "results": {
        "live": {
          "act": 5.0,
          "trail": 2.0,
          "sl": -10.0,
          "exit_pnl_pct": -12.88,
          "exit_pnl_usd": -2.58,
          "exit_reason": "SL",
          "exit_time": "2026-02-18T09:17:33.682733+09:00",
          "highest_pnl": 14.51,
          "trail_activated": true
        },
        "conservative": {
          "act": 8.0,
          "trail": 3.0,
          "sl": -10.0,
          "exit_pnl_pct": -12.88,
          "exit_pnl_usd": -2.58,
          "exit_reason": "SL",
          "exit_time": "2026-02-18T09:17:33.682733+09:00",
          "highest_pnl": 14.51,
          "trail_activated": true
        },
        "current": {
          "act": 5.0,
          "trail": 3.0,
          "sl": -10.0,
          "exit_pnl_pct": -12.88,
          "exit_pnl_usd": -2.58,
          "exit_reason": "SL",
          "exit_time": "2026-02-18T09:17:33.682733+09:00",
          "highest_pnl": 14.51,
          "trail_activated": true
        },
        "moderate": {
          "act": 3.0,
          "trail": 2.0,
          "sl": -10.0,
          "exit_pnl_pct": -12.88,
          "exit_pnl_usd": -2.58,
          "exit_reason": "SL",
          "exit_time": "2026-02-18T09:17:33.682733+09:00",
          "highest_pnl": 14.51,
          "trail_activated": true
        },
        "tight": {
          "act": 3.0,
          "trail": 1.5,
          "sl": -10.0,
          "exit_pnl_pct": -12.88,
          "exit_pnl_usd": -2.58,
          "exit_reason": "SL",
          "exit_time": "2026-02-18T09:17:33.682733+09:00",
          "highest_pnl": 14.51,
          "trail_activated": true
        },
        "aggressive": {
          "act": 2.0,
          "trail": 1.0,
          "sl": -10.0,
          "exit_pnl_pct": -12.88,
          "exit_pnl_usd": -2.58,
          "exit_reason": "SL",
          "exit_time": "2026-02-18T09:17:33.682733+09:00",
          "highest_pnl": 14.51,
          "trail_activated": true
        },
        "wide_trail": {
          "act": 5.0,
          "trail": 2.0,
          "sl": -15.0,
          "exit_pnl_pct": -12.88,
          "exit_pnl_usd": -2.58,
          "exit_reason": "TRAIL",
          "exit_time": "2026-02-18T09:17:33.682733+09:00",
          "highest_pnl": 14.51,
          "trail_activated": true
        },
        "wide_sl15": {
          "act": 5.0,
          "trail": 3.0,
          "sl": -15.0,
          "exit_pnl_pct": -12.88,
          "exit_pnl_usd": -2.58,
          "exit_reason": "TRAIL",
          "exit_time": "2026-02-18T09:17:33.682733+09:00",
          "highest_pnl": 14.51,
          "trail_activated": true
        }
      },
      "momentum_exit": {
        "param_used": "current",
        "buys_1h": 4487,
        "exit_pnl_pct": -12.88,
        "exit_pnl_usd": -2.58,
        "exit_reason": "SL"
      },
      "filter_match": {
        "live": true
      }
    },
    {
      "address": "C7V47ci5u2Ak3VYb62a1obLTY74BLFxLB7d2NLKRpump",
      "symbol": "AI",
      "entry_time": "2026-02-18T09:13:34.878845+09:00",
      "entry_price": 0.0005253125,
      "amount_usd": 20.0,
      "score": 52.065730011801165,
      "grade": "B",
      "liquidity": 57018.29,
      "volume_24h": 59166.68,
      "token_age_min": 4771.9,
      "peak_pnl_pct": 7.93,
      "price_points": 21,
      "pc_5m": 15.25,
      "pc_1h": 14.95,
      "buys_1h": 9,
      "sells_1h": 4,
      "bs_ratio": 0.0,
      "completed_at": "2026-02-18T09:17:55.017691+09:00",
      "results": {
        "live": {
          "act": 5.0,
          "trail": 2.0,
          "sl": -10.0,
          "exit_pnl_pct": -2.08,
          "exit_pnl_usd": -0.42,
          "exit_reason": "TRAIL",
          "exit_time": "2026-02-18T09:14:40.349614+09:00",
          "highest_pnl": 5.87,
          "trail_activated": true
        },
        "conservative": {
          "act": 8.0,
          "trail": 3.0,
          "sl": -10.0,
          "exit_pnl_pct": -14.9,
          "exit_pnl_usd": -2.98,
          "exit_reason": "SL",
          "exit_time": "2026-02-18T09:17:55.017159+09:00",
          "highest_pnl": 0.0,
          "trail_activated": false
        },
        "current": {
          "act": 5.0,
          "trail": 3.0,
          "sl": -10.0,
          "exit_pnl_pct": -2.08,
          "exit_pnl_usd": -0.42,
          "exit_reason": "TRAIL",
          "exit_time": "2026-02-18T09:14:40.349614+09:00",
          "highest_pnl": 5.87,
          "trail_activated": true
        },
        "moderate": {
          "act": 3.0,
          "trail": 2.0,
          "sl": -10.0,
          "exit_pnl_pct": -2.08,
          "exit_pnl_usd": -0.42,
          "exit_reason": "TRAIL",
          "exit_time": "2026-02-18T09:14:40.349614+09:00",
          "highest_pnl": 5.87,
          "trail_activated": true
        },
        "tight": {
          "act": 3.0,
          "trail": 1.5,
          "sl": -10.0,
          "exit_pnl_pct": -2.08,
          "exit_pnl_usd": -0.42,
          "exit_reason": "TRAIL",
          "exit_time": "2026-02-18T09:14:40.349614+09:00",
          "highest_pnl": 5.87,
          "trail_activated": true
        },
        "aggressive": {
          "act": 2.0,
          "trail": 1.0,
          "sl": -10.0,
          "exit_pnl_pct": -2.08,
          "exit_pnl_usd": -0.42,
          "exit_reason": "TRAIL",
          "exit_time": "2026-02-18T09:14:40.349614+09:00",
          "highest_pnl": 5.87,
          "trail_activated": true
        },
        "wide_trail": {
          "act": 5.0,
          "trail": 2.0,
          "sl": -15.0,
          "exit_pnl_pct": -2.08,
          "exit_pnl_usd": -0.42,
          "exit_reason": "TRAIL",
          "exit_time": "2026-02-18T09:14:40.349614+09:00",
          "highest_pnl": 5.87,
          "trail_activated": true
        },
        "wide_sl15": {
          "act": 5.0,
          "trail": 3.0,
          "sl": -15.0,
          "exit_pnl_pct": -2.08,
          "exit_pnl_usd": -0.42,
          "exit_reason": "TRAIL",
          "exit_time": "2026-02-18T09:14:40.349614+09:00",
          "highest_pnl": 5.87,
          "trail_activated": true
        }
      },
      "momentum_exit": {
        "param_used": "conservative",
        "buys_1h": 9,
        "exit_pnl_pct": -14.9,
        "exit_pnl_usd": -2.98,
        "exit_reason": "SL"
      },
      "filter_match": {
        "live": true
      }
    },
    {
      "address": "4Aar9R14YMbEie6yh8WcH1gWXrBtfucoFjw6SpjXpump",
      "symbol": "OmegaX",
      "entry_time": "2026-02-18T08:26:50.407884+09:00",
      "entry_price": 0.0009937375,
      "amount_usd": 20.0,
      "score": 57.81328533339356,
      "grade": "B",
      "liquidity": 77055.05,
      "volume_24h": 144802.72,
      "token_age_min": 8832.0,
      "peak_pnl_pct": 9.5,
      "price_points": 245,
      "pc_5m": -3.29,
      "pc_1h": 25.25,
      "buys_1h": 1595,
      "sells_1h": 71,
      "bs_ratio": 22.46,
      "completed_at": "2026-02-18T09:20:54.251632+09:00",
      "results": {
        "live": {
          "act": 5.0,
          "trail": 2.0,
          "sl": -10.0,
          "exit_pnl_pct": 7.04,
          "exit_pnl_usd": 1.41,
          "exit_reason": "TRAIL",
          "exit_time": "2026-02-18T09:15:12.613020+09:00",
          "highest_pnl": 9.5,
          "trail_activated": true
        },
        "conservative": {
          "act": 8.0,
          "trail": 3.0,
          "sl": -10.0,
          "exit_pnl_pct": 5.77,
          "exit_pnl_usd": 1.15,
          "exit_reason": "TRAIL",
          "exit_time": "2026-02-18T09:20:54.247957+09:00",
          "highest_pnl": 9.5,
          "trail_activated": true
        },
        "current": {
          "act": 5.0,
          "trail": 3.0,
          "sl": -10.0,
          "exit_pnl_pct": 5.77,
          "exit_pnl_usd": 1.15,
          "exit_reason": "TRAIL",
          "exit_time": "2026-02-18T09:20:54.247957+09:00",
          "highest_pnl": 9.5,
          "trail_activated": true
        },
        "moderate": {
          "act": 3.0,
          "trail": 2.0,
          "sl": -10.0,
          "exit_pnl_pct": 7.04,
          "exit_pnl_usd": 1.41,
          "exit_reason": "TRAIL",
          "exit_time": "2026-02-18T09:15:12.613020+09:00",
          "highest_pnl": 9.5,
          "trail_activated": true
        },
        "tight": {
          "act": 3.0,
          "trail": 1.5,
          "sl": -10.0,
          "exit_pnl_pct": 6.75,
          "exit_pnl_usd": 1.35,
          "exit_reason": "TRAIL",
          "exit_time": "2026-02-18T09:07:02.829441+09:00",
          "highest_pnl": 8.32,
          "trail_activated": true
        },
        "aggressive": {
          "act": 2.0,
          "trail": 1.0,
          "sl": -10.0,
          "exit_pnl_pct": 3.12,
          "exit_pnl_usd": 0.62,
          "exit_reason": "TRAIL",
          "exit_time": "2026-02-18T09:04:30.781898+09:00",
          "highest_pnl": 4.3,
          "trail_activated": true
        },
        "wide_trail": {
          "act": 5.0,
          "trail": 2.0,
          "sl": -15.0,
          "exit_pnl_pct": 7.04,
          "exit_pnl_usd": 1.41,
          "exit_reason": "TRAIL",
          "exit_time": "2026-02-18T09:15:12.613020+09:00",
          "highest_pnl": 9.5,
          "trail_activated": true
        },
        "wide_sl15": {
          "act": 5.0,
          "trail": 3.0,
          "sl": -15.0,
          "exit_pnl_pct": 5.77,
          "exit_pnl_usd": 1.15,
          "exit_reason": "TRAIL",
          "exit_time": "2026-02-18T09:20:54.247957+09:00",
          "highest_pnl": 9.5,
          "trail_activated": true
        }
      },
      "momentum_exit": {
        "param_used": "current",
        "buys_1h": 1595,
        "exit_pnl_pct": 5.77,
        "exit_pnl_usd": 1.15,
        "exit_reason": "TRAIL"
      },
      "filter_match": {
        "live": true
      }
    },
    {
      "address": "3bzeQJqDPfQQbxJ6VmtMkXyyQEJrj9HS1SMvHR1Hpump",
      "symbol": "WILSON",
      "entry_time": "2026-02-18T08:49:44.012396+09:00",
      "entry_price": 0.00032584749999999994,
      "amount_usd": 20.0,
      "score": 52.6065953266196,
      "grade": "B",
      "liquidity": 49255.13,
      "volume_24h": 578849.13,
      "token_age_min": 28206.0,
      "peak_pnl_pct": 0.0,
      "price_points": 245,
      "pc_5m": -4.16,
      "pc_1h": 25.83,
      "buys_1h": 58,
      "sells_1h": 48,
      "bs_ratio": 1.21,
      "completed_at": "2026-02-18T09:48:09.074102+09:00",
      "results": {
        "live": {
          "act": 5.0,
          "trail": 2.0,
          "sl": -10.0,
          "exit_pnl_pct": -10.56,
          "exit_pnl_usd": -2.11,
          "exit_reason": "SL",
          "exit_time": "2026-02-18T08:55:10.690803+09:00",
          "highest_pnl": 0.0,
          "trail_activated": false
        },
        "conservative": {
          "act": 8.0,
          "trail": 3.0,
          "sl": -10.0,
          "exit_pnl_pct": -10.56,
          "exit_pnl_usd": -2.11,
          "exit_reason": "SL",
          "exit_time": "2026-02-18T08:55:10.690803+09:00",
          "highest_pnl": 0.0,
          "trail_activated": false
        },
        "current": {
          "act": 5.0,
          "trail": 3.0,
          "sl": -10.0,
          "exit_pnl_pct": -10.56,
          "exit_pnl_usd": -2.11,
          "exit_reason": "SL",
          "exit_time": "2026-02-18T08:55:10.690803+09:00",
          "highest_pnl": 0.0,
          "trail_activated": false
        },
        "moderate": {
          "act": 3.0,
          "trail": 2.0,
          "sl": -10.0,
          "exit_pnl_pct": -10.56,
          "exit_pnl_usd": -2.11,
          "exit_reason": "SL",
          "exit_time": "2026-02-18T08:55:10.690803+09:00",
          "highest_pnl": 0.0,
          "trail_activated": false
        },
        "tight": {
          "act": 3.0,
          "trail": 1.5,
          "sl": -10.0,
          "exit_pnl_pct": -10.56,
          "exit_pnl_usd": -2.11,
          "exit_reason": "SL",
          "exit_time": "2026-02-18T08:55:10.690803+09:00",
          "highest_pnl": 0.0,
          "trail_activated": false
        },
        "aggressive": {
          "act": 2.0,
          "trail": 1.0,
          "sl": -10.0,
          "exit_pnl_pct": -10.56,
          "exit_pnl_usd": -2.11,
          "exit_reason": "SL",
          "exit_time": "2026-02-18T08:55:10.690803+09:00",
          "highest_pnl": 0.0,
          "trail_activated": false
        },
        "wide_trail": {
          "act": 5.0,
          "trail": 2.0,
          "sl": -15.0,
          "exit_pnl_pct": -15.35,
          "exit_pnl_usd": -3.07,
          "exit_reason": "SL",
          "exit_time": "2026-02-18T09:48:09.071925+09:00",
          "highest_pnl": 0.0,
          "trail_activated": false
        },
        "wide_sl15": {
          "act": 5.0,
          "trail": 3.0,
          "sl": -15.0,
          "exit_pnl_pct": -15.35,
          "exit_pnl_usd": -3.07,
          "exit_reason": "SL",
          "exit_time": "2026-02-18T09:48:09.071925+09:00",
          "highest_pnl": 0.0,
          "trail_activated": false
        }
      },
      "momentum_exit": {
        "param_used": "aggressive",
        "buys_1h": 58,
        "exit_pnl_pct": -10.56,
        "exit_pnl_usd": -2.11,
        "exit_reason": "SL"
      },
      "filter_match": {
        "live": true
      }
    },
    {
      "address": "B4K4GYu2PunhWFGCCMrHdNR18moaW4eoSNSdHPBMpump",
      "symbol": "EGOD",
      "entry_time": "2026-02-18T09:43:37.913847+09:00",
      "entry_price": 9.60425e-05,
      "amount_usd": 20.0,
      "score": 49.95637879396941,
      "grade": "C",
      "liquidity": 28657.75,
      "volume_24h": 986297.05,
      "token_age_min": 1638.0,
      "peak_pnl_pct": 16.44,
      "price_points": 35,
      "pc_5m": 19.54,
      "pc_1h": 28.62,
      "buys_1h": 151,
      "sells_1h": 122,
      "bs_ratio": 1.24,
      "completed_at": "2026-02-18T09:52:37.654277+09:00",
      "results": {
        "live": {
          "act": 5.0,
          "trail": 2.0,
          "sl": -10.0,
          "exit_pnl_pct": -10.61,
          "exit_pnl_usd": -2.12,
          "exit_reason": "SL",
          "exit_time": "2026-02-18T09:46:31.114292+09:00",
          "highest_pnl": 0.0,
          "trail_activated": false
        },
        "conservative": {
          "act": 8.0,
          "trail": 3.0,
          "sl": -10.0,
          "exit_pnl_pct": -10.61,
          "exit_pnl_usd": -2.12,
          "exit_reason": "SL",
          "exit_time": "2026-02-18T09:46:31.114292+09:00",
          "highest_pnl": 0.0,
          "trail_activated": false
        },
        "current": {
          "act": 5.0,
          "trail": 3.0,
          "sl": -10.0,
          "exit_pnl_pct": -10.61,
          "exit_pnl_usd": -2.12,
          "exit_reason": "SL",
          "exit_time": "2026-02-18T09:46:31.114292+09:00",
          "highest_pnl": 0.0,
          "trail_activated": false
        },
        "moderate": {
          "act": 3.0,
          "trail": 2.0,
          "sl": -10.0,
          "exit_pnl_pct": -10.61,
          "exit_pnl_usd": -2.12,
          "exit_reason": "SL",
          "exit_time": "2026-02-18T09:46:31.114292+09:00",
          "highest_pnl": 0.0,
          "trail_activated": false
        },
        "tight": {
          "act": 3.0,
          "trail": 1.5,
          "sl": -10.0,
          "exit_pnl_pct": -10.61,
          "exit_pnl_usd": -2.12,
          "exit_reason": "SL",
          "exit_time": "2026-02-18T09:46:31.114292+09:00",
          "highest_pnl": 0.0,
          "trail_activated": false
        },
        "aggressive": {
          "act": 2.0,
          "trail": 1.0,
          "sl": -10.0,
          "exit_pnl_pct": -10.61,
          "exit_pnl_usd": -2.12,
          "exit_reason": "SL",
          "exit_time": "2026-02-18T09:46:31.114292+09:00",
          "highest_pnl": 0.0,
          "trail_activated": false
        },
        "wide_trail": {
          "act": 5.0,
          "trail": 2.0,
          "sl": -15.0,
          "exit_pnl_pct": 10.86,
          "exit_pnl_usd": 2.17,
          "exit_reason": "TRAIL",
          "exit_time": "2026-02-18T09:50:08.018694+09:00",
          "highest_pnl": 13.7,
          "trail_activated": true
        },
        "wide_sl15": {
          "act": 5.0,
          "trail": 3.0,
          "sl": -15.0,
          "exit_pnl_pct": 13.4,
          "exit_pnl_usd": 2.68,
          "exit_reason": "TRAIL",
          "exit_time": "2026-02-18T09:52:37.653975+09:00",
          "highest_pnl": 16.44,
          "trail_activated": true
        }
      },
      "momentum_exit": {
        "param_used": "aggressive",
        "buys_1h": 151,
        "exit_pnl_pct": -10.61,
        "exit_pnl_usd": -2.12,
        "exit_reason": "SL"
      },
      "filter_match": {
        "live": true
      }
    },
    {
      "address": "BzyKa1FGjs2EUpu3GGDibY4xdygn5evAiRboKmETpump",
      "symbol": "TRENCH",
      "entry_time": "2026-02-18T08:26:50.409112+09:00",
      "entry_price": 0.0002627075,
      "amount_usd": 20.0,
      "score": 49.958618689012866,
      "grade": "C",
      "liquidity": 43466.61,
      "volume_24h": 191661.43,
      "token_age_min": 5807.3,
      "peak_pnl_pct": 6.4,
      "price_points": 415,
      "pc_5m": 1.41,
      "pc_1h": 4.67,
      "buys_1h": 131,
      "sells_1h": 60,
      "bs_ratio": 0.0,
      "completed_at": "2026-02-18T10:04:27.260783+09:00",
      "results": {
        "live": {
          "act": 5.0,
          "trail": 2.0,
          "sl": -10.0,
          "exit_pnl_pct": -1.06,
          "exit_pnl_usd": -0.21,
          "exit_reason": "TRAIL",
          "exit_time": "2026-02-18T08:42:12.842941+09:00",
          "highest_pnl": 6.4,
          "trail_activated": true
        },
        "conservative": {
          "act": 8.0,
          "trail": 3.0,
          "sl": -10.0,
          "exit_pnl_pct": -16.2,
          "exit_pnl_usd": -3.24,
          "exit_reason": "SL",
          "exit_time": "2026-02-18T10:04:27.257181+09:00",
          "highest_pnl": 0.0,
          "trail_activated": false
        },
        "current": {
          "act": 5.0,
          "trail": 3.0,
          "sl": -10.0,
          "exit_pnl_pct": -1.06,
          "exit_pnl_usd": -0.21,
          "exit_reason": "TRAIL",
          "exit_time": "2026-02-18T08:42:12.842941+09:00",
          "highest_pnl": 6.4,
          "trail_activated": true
        },
        "moderate": {
          "act": 3.0,
          "trail": 2.0,
          "sl": -10.0,
          "exit_pnl_pct": -1.06,
          "exit_pnl_usd": -0.21,
          "exit_reason": "TRAIL",
          "exit_time": "2026-02-18T08:42:12.842941+09:00",
          "highest_pnl": 6.4,
          "trail_activated": true
        },
        "tight": {
          "act": 3.0,
          "trail": 1.5,
          "sl": -10.0,
          "exit_pnl_pct": -1.06,
          "exit_pnl_usd": -0.21,
          "exit_reason": "TRAIL",
          "exit_time": "2026-02-18T08:42:12.842941+09:00",
          "highest_pnl": 6.4,
          "trail_activated": true
        },
        "aggressive": {
          "act": 2.0,
          "trail": 1.0,
          "sl": -10.0,
          "exit_pnl_pct": -1.06,
          "exit_pnl_usd": -0.21,
          "exit_reason": "TRAIL",
          "exit_time": "2026-02-18T08:42:12.842941+09:00",
          "highest_pnl": 6.4,
          "trail_activated": true
        },
        "wide_trail": {
          "act": 5.0,
          "trail": 2.0,
          "sl": -15.0,
          "exit_pnl_pct": -1.06,
          "exit_pnl_usd": -0.21,
          "exit_reason": "TRAIL",
          "exit_time": "2026-02-18T08:42:12.842941+09:00",
          "highest_pnl": 6.4,
          "trail_activated": true
        },
        "wide_sl15": {
          "act": 5.0,
          "trail": 3.0,
          "sl": -15.0,
          "exit_pnl_pct": -1.06,
          "exit_pnl_usd": -0.21,
          "exit_reason": "TRAIL",
          "exit_time": "2026-02-18T08:42:12.842941+09:00",
          "highest_pnl": 6.4,
          "trail_activated": true
        }
      },
      "momentum_exit": {
        "param_used": "aggressive",
        "buys_1h": 131,
        "exit_pnl_pct": -1.06,
        "exit_pnl_usd": -0.21,
        "exit_reason": "TRAIL"
      },
      "filter_match": {
        "live": true
      }
    },
    {
      "address": "9HHrikqNLYvfXzxtNV8pvPLrWbDGG4mZkVpaKBcvgLyu",
      "symbol": "buddy",
      "entry_time": "2026-02-18T10:05:39.349090+09:00",
      "entry_price": 0.0001429875,
      "amount_usd": 20.0,
      "score": 41.136958205515626,
      "grade": "C",
      "liquidity": 33198.07,
      "volume_24h": 62206.16,
      "token_age_min": 28279.7,
      "peak_pnl_pct": 0.0,
      "price_points": 26,
      "pc_5m": 4.19,
      "pc_1h": 5.93,
      "buys_1h": 62,
      "sells_1h": 76,
      "bs_ratio": 0.0,
      "completed_at": "2026-02-18T10:11:27.810808+09:00",
      "results": {
        "live": {
          "act": 5.0,
          "trail": 2.0,
          "sl": -10.0,
          "exit_pnl_pct": -17.29,
          "exit_pnl_usd": -3.46,
          "exit_reason": "SL",
          "exit_time": "2026-02-18T10:11:27.810283+09:00",
          "highest_pnl": 0.0,
          "trail_activated": false
        },
        "conservative": {
          "act": 8.0,
          "trail": 3.0,
          "sl": -10.0,
          "exit_pnl_pct": -17.29,
          "exit_pnl_usd": -3.46,
          "exit_reason": "SL",
          "exit_time": "2026-02-18T10:11:27.810283+09:00",
          "highest_pnl": 0.0,
          "trail_activated": false
        },
        "current": {
          "act": 5.0,
          "trail": 3.0,
          "sl": -10.0,
          "exit_pnl_pct": -17.29,
          "exit_pnl_usd": -3.46,
          "exit_reason": "SL",
          "exit_time": "2026-02-18T10:11:27.810283+09:00",
          "highest_pnl": 0.0,
          "trail_activated": false
        },
        "moderate": {
          "act": 3.0,
          "trail": 2.0,
          "sl": -10.0,
          "exit_pnl_pct": -17.29,
          "exit_pnl_usd": -3.46,
          "exit_reason": "SL",
          "exit_time": "2026-02-18T10:11:27.810283+09:00",
          "highest_pnl": 0.0,
          "trail_activated": false
        },
        "tight": {
          "act": 3.0,
          "trail": 1.5,
          "sl": -10.0,
          "exit_pnl_pct": -17.29,
          "exit_pnl_usd": -3.46,
          "exit_reason": "SL",
          "exit_time": "2026-02-18T10:11:27.810283+09:00",
          "highest_pnl": 0.0,
          "trail_activated": false
        },
        "aggressive": {
          "act": 2.0,
          "trail": 1.0,
          "sl": -10.0,
          "exit_pnl_pct": -17.29,
          "exit_pnl_usd": -3.46,
          "exit_reason": "SL",
          "exit_time": "2026-02-18T10:11:27.810283+09:00",
          "highest_pnl": 0.0,
          "trail_activated": false
        },
        "wide_trail": {
          "act": 5.0,
          "trail": 2.0,
          "sl": -15.0,
          "exit_pnl_pct": -17.29,
          "exit_pnl_usd": -3.46,
          "exit_reason": "SL",
          "exit_time": "2026-02-18T10:11:27.810283+09:00",
          "highest_pnl": 0.0,
          "trail_activated": false
        },
        "wide_sl15": {
          "act": 5.0,
          "trail": 3.0,
          "sl": -15.0,
          "exit_pnl_pct": -17.29,
          "exit_pnl_usd": -3.46,
          "exit_reason": "SL",
          "exit_time": "2026-02-18T10:11:27.810283+09:00",
          "highest_pnl": 0.0,
          "trail_activated": false
        }
      },
      "momentum_exit": {
        "param_used": "aggressive",
        "buys_1h": 62,
        "exit_pnl_pct": -17.29,
        "exit_pnl_usd": -3.46,
        "exit_reason": "SL"
      },
      "filter_match": {
        "live": false
      }
    },
    {
      "address": "GQz5ThKHNcuAvMKA8rCPSdoFUoApk9Fi8qB9m3Gqpump",
      "symbol": "SAN",
      "entry_time": "2026-02-18T08:26:50.410965+09:00",
      "entry_price": 0.0014770249999999999,
      "amount_usd": 20.0,
      "score": 38.97668477251207,
      "grade": "C",
      "liquidity": 94006.57,
      "volume_24h": 116333.68,
      "token_age_min": 14714.3,
      "peak_pnl_pct": 30.24,
      "price_points": 497,
      "pc_5m": -0.52,
      "pc_1h": -2.3,
      "buys_1h": 1013,
      "sells_1h": 10,
      "bs_ratio": 0.0,
      "completed_at": "2026-02-18T10:26:36.482562+09:00",
      "results": {
        "live": {
          "act": 5.0,
          "trail": 2.0,
          "sl": -10.0,
          "exit_pnl_pct": 28.06,
          "exit_pnl_usd": 5.61,
          "exit_reason": "TRAIL",
          "exit_time": "2026-02-18T10:16:03.324010+09:00",
          "highest_pnl": 30.24,
          "trail_activated": true
        },
        "conservative": {
          "act": 8.0,
          "trail": 3.0,
          "sl": -10.0,
          "exit_pnl_pct": 25.16,
          "exit_pnl_usd": 5.03,
          "exit_reason": "TRAIL",
          "exit_time": "2026-02-18T10:26:36.479564+09:00",
          "highest_pnl": 30.24,
          "trail_activated": true
        },
        "current": {
          "act": 5.0,
          "trail": 3.0,
          "sl": -10.0,
          "exit_pnl_pct": 25.16,
          "exit_pnl_usd": 5.03,
          "exit_reason": "TRAIL",
          "exit_time": "2026-02-18T10:26:36.479564+09:00",
          "highest_pnl": 30.24,
          "trail_activated": true
        },
        "moderate": {
          "act": 3.0,
          "trail": 2.0,
          "sl": -10.0,
          "exit_pnl_pct": 28.06,
          "exit_pnl_usd": 5.61,
          "exit_reason": "TRAIL",
          "exit_time": "2026-02-18T10:16:03.324010+09:00",
          "highest_pnl": 30.24,
          "trail_activated": true
        },
        "tight": {
          "act": 3.0,
          "trail": 1.5,
          "sl": -10.0,
          "exit_pnl_pct": 28.72,
          "exit_pnl_usd": 5.74,
          "exit_reason": "TRAIL",
          "exit_time": "2026-02-18T09:58:32.066685+09:00",
          "highest_pnl": 30.24,
          "trail_activated": true
        },
        "aggressive": {
          "act": 2.0,
          "trail": 1.0,
          "sl": -10.0,
          "exit_pnl_pct": 5.29,
          "exit_pnl_usd": 1.06,
          "exit_reason": "TRAIL",
          "exit_time": "2026-02-18T09:21:14.682063+09:00",
          "highest_pnl": 6.48,
          "trail_activated": true
        },
        "wide_trail": {
          "act": 5.0,
          "trail": 2.0,
          "sl": -15.0,
          "exit_pnl_pct": 28.06,
          "exit_pnl_usd": 5.61,
          "exit_reason": "TRAIL",
          "exit_time": "2026-02-18T10:16:03.324010+09:00",
          "highest_pnl": 30.24,
          "trail_activated": true
        },
        "wide_sl15": {
          "act": 5.0,
          "trail": 3.0,
          "sl": -15.0,
          "exit_pnl_pct": 25.16,
          "exit_pnl_usd": 5.03,
          "exit_reason": "TRAIL",
          "exit_time": "2026-02-18T10:26:36.479564+09:00",
          "highest_pnl": 30.24,
          "trail_activated": true
        }
      },
      "momentum_exit": {
        "param_used": "aggressive",
        "buys_1h": 1013,
        "exit_pnl_pct": 5.29,
        "exit_pnl_usd": 1.06,
        "exit_reason": "TRAIL"
      },
      "filter_match": {
        "live": true
      }
    },
    {
      "address": "6p6xgHyF7AeE6TZkSmFsko444wqoP15icUSqi2jfGiPN",
      "symbol": "TRUMP",
      "entry_time": "2026-02-18T08:26:50.409587+09:00",
      "entry_price": 3.53625,
      "amount_usd": 20.0,
      "score": 48.5,
      "grade": "C",
      "liquidity": 28945391.55,
      "volume_24h": 3474927.78,
      "token_age_min": 569655.7,
      "peak_pnl_pct": 0.0,
      "price_points": 499,
      "pc_5m": 0.1,
      "pc_1h": 0.9,
      "buys_1h": 61,
      "sells_1h": 43,
      "bs_ratio": 0.0,
      "completed_at": "2026-02-18T10:26:58.045249+09:00",
      "results": {
        "live": {
          "act": 5.0,
          "trail": 2.0,
          "sl": -10.0,
          "exit_pnl_pct": -4.6,
          "exit_pnl_usd": -0.92,
          "exit_reason": "TIMEOUT",
          "exit_time": "2026-02-18T10:26:58.040444+09:00",
          "highest_pnl": 0.0,
          "trail_activated": false
        },
        "conservative": {
          "act": 8.0,
          "trail": 3.0,
          "sl": -10.0,
          "exit_pnl_pct": -4.6,
          "exit_pnl_usd": -0.92,
          "exit_reason": "TIMEOUT",
          "exit_time": "2026-02-18T10:26:58.040444+09:00",
          "highest_pnl": 0.0,
          "trail_activated": false
        },
        "current": {
          "act": 5.0,
          "trail": 3.0,
          "sl": -10.0,
          "exit_pnl_pct": -4.6,
          "exit_pnl_usd": -0.92,
          "exit_reason": "TIMEOUT",
          "exit_time": "2026-02-18T10:26:58.040444+09:00",
          "highest_pnl": 0.0,
          "trail_activated": false
        },
        "moderate": {
          "act": 3.0,
          "trail": 2.0,
          "sl": -10.0,
          "exit_pnl_pct": -4.6,
          "exit_pnl_usd": -0.92,
          "exit_reason": "TIMEOUT",
          "exit_time": "2026-02-18T10:26:58.040444+09:00",
          "highest_pnl": 0.0,
          "trail_activated": false
        },
        "tight": {
          "act": 3.0,
          "trail": 1.5,
          "sl": -10.0,
          "exit_pnl_pct": -4.6,
          "exit_pnl_usd": -0.92,
          "exit_reason": "TIMEOUT",
          "exit_time": "2026-02-18T10:26:58.040444+09:00",
          "highest_pnl": 0.0,
          "trail_activated": false
        },
        "aggressive": {
          "act": 2.0,
          "trail": 1.0,
          "sl": -10.0,
          "exit_pnl_pct": -4.6,
          "exit_pnl_usd": -0.92,
          "exit_reason": "TIMEOUT",
          "exit_time": "2026-02-18T10:26:58.040444+09:00",
          "highest_pnl": 0.0,
          "trail_activated": false
        },
        "wide_trail": {
          "act": 5.0,
          "trail": 2.0,
          "sl": -15.0,
          "exit_pnl_pct": -4.6,
          "exit_pnl_usd": -0.92,
          "exit_reason": "TIMEOUT",
          "exit_time": "2026-02-18T10:26:58.040444+09:00",
          "highest_pnl": 0.0,
          "trail_activated": false
        },
        "wide_sl15": {
          "act": 5.0,
          "trail": 3.0,
          "sl": -15.0,
          "exit_pnl_pct": -4.6,
          "exit_pnl_usd": -0.92,
          "exit_reason": "TIMEOUT",
          "exit_time": "2026-02-18T10:26:58.040444+09:00",
          "highest_pnl": 0.0,
          "trail_activated": false
        }
      },
      "momentum_exit": {
        "param_used": "aggressive",
        "buys_1h": 61,
        "exit_pnl_pct": -4.6,
        "exit_pnl_usd": -0.92,
        "exit_reason": "TIMEOUT"
      },
      "filter_match": {
        "live": true
      }
    },
    {
      "address": "FsXJHch6cj9TyZGm1kfMwt8S8oATCEr6ccqWFp3Xpump",
      "symbol": "SOULGUY",
      "entry_time": "2026-02-18T08:26:50.410518+09:00",
      "entry_price": 0.0003965725,
      "amount_usd": 20.0,
      "score": 42.27223009047644,
      "grade": "C",
      "liquidity": 68811.2,
      "volume_24h": 144211.54,
      "token_age_min": 131799.1,
      "peak_pnl_pct": 4.0,
      "price_points": 499,
      "pc_5m": -1.47,
      "pc_1h": 1.33,
      "buys_1h": 126,
      "sells_1h": 101,
      "bs_ratio": 0.0,
      "completed_at": "2026-02-18T10:26:58.046307+09:00",
      "results": {
        "live": {
          "act": 5.0,
          "trail": 2.0,
          "sl": -10.0,
          "exit_pnl_pct": -0.08,
          "exit_pnl_usd": -0.02,
          "exit_reason": "TIMEOUT",
          "exit_time": "2026-02-18T10:26:58.041820+09:00",
          "highest_pnl": 0.0,
          "trail_activated": false
        },
        "conservative": {
          "act": 8.0,
          "trail": 3.0,
          "sl": -10.0,
          "exit_pnl_pct": -0.08,
          "exit_pnl_usd": -0.02,
          "exit_reason": "TIMEOUT",
          "exit_time": "2026-02-18T10:26:58.041820+09:00",
          "highest_pnl": 0.0,
          "trail_activated": false
        },
        "current": {
          "act": 5.0,
          "trail": 3.0,
          "sl": -10.0,
          "exit_pnl_pct": -0.08,
          "exit_pnl_usd": -0.02,
          "exit_reason": "TIMEOUT",
          "exit_time": "2026-02-18T10:26:58.041820+09:00",
          "highest_pnl": 0.0,
          "trail_activated": false
        },
        "moderate": {
          "act": 3.0,
          "trail": 2.0,
          "sl": -10.0,
          "exit_pnl_pct": 1.69,
          "exit_pnl_usd": 0.34,
          "exit_reason": "TRAIL",
          "exit_time": "2026-02-18T10:04:38.423238+09:00",
          "highest_pnl": 3.78,
          "trail_activated": true
        },
        "tight": {
          "act": 3.0,
          "trail": 1.5,
          "sl": -10.0,
          "exit_pnl_pct": 1.69,
          "exit_pnl_usd": 0.34,
          "exit_reason": "TRAIL",
          "exit_time": "2026-02-18T10:04:38.423238+09:00",
          "highest_pnl": 3.78,
          "trail_activated": true
        },
        "aggressive": {
          "act": 2.0,
          "trail": 1.0,
          "sl": -10.0,
          "exit_pnl_pct": 0.75,
          "exit_pnl_usd": 0.15,
          "exit_reason": "TRAIL",
          "exit_time": "2026-02-18T09:17:33.679658+09:00",
          "highest_pnl": 2.82,
          "trail_activated": true
        },
        "wide_trail": {
          "act": 5.0,
          "trail": 2.0,
          "sl": -15.0,
          "exit_pnl_pct": -0.08,
          "exit_pnl_usd": -0.02,
          "exit_reason": "TIMEOUT",
          "exit_time": "2026-02-18T10:26:58.041820+09:00",
          "highest_pnl": 0.0,
          "trail_activated": false
        },
        "wide_sl15": {
          "act": 5.0,
          "trail": 3.0,
          "sl": -15.0,
          "exit_pnl_pct": -0.08,
          "exit_pnl_usd": -0.02,
          "exit_reason": "TIMEOUT",
          "exit_time": "2026-02-18T10:26:58.041820+09:00",
          "highest_pnl": 0.0,
          "trail_activated": false
        }
      },
      "momentum_exit": {
        "param_used": "aggressive",
        "buys_1h": 126,
        "exit_pnl_pct": 0.75,
        "exit_pnl_usd": 0.15,
        "exit_reason": "TRAIL"
      },
      "filter_match": {
        "live": true
      }
    },
    {
      "address": "DRLNhjM7jusYFPF1qade1dBD1qhgds7oAfdKs51Vpump",
      "symbol": "SOL",
      "entry_time": "2026-02-18T08:29:01.272668+09:00",
      "entry_price": 0.00011807999999999998,
      "amount_usd": 20.0,
      "score": 49.163642770653354,
      "grade": "C",
      "liquidity": 30185.72,
      "volume_24h": 6984.29,
      "token_age_min": 18276.6,
      "peak_pnl_pct": 0.0,
      "price_points": 499,
      "pc_5m": 0.25,
      "pc_1h": 0.48,
      "buys_1h": 9,
      "sells_1h": 1,
      "bs_ratio": 0.0,
      "completed_at": "2026-02-18T10:29:08.863370+09:00",
      "results": {
        "live": {
          "act": 5.0,
          "trail": 2.0,
          "sl": -10.0,
          "exit_pnl_pct": -10.33,
          "exit_pnl_usd": -2.07,
          "exit_reason": "SL",
          "exit_time": "2026-02-18T10:01:43.869746+09:00",
          "highest_pnl": 0.0,
          "trail_activated": false
        },
        "conservative": {
          "act": 8.0,
          "trail": 3.0,
          "sl": -10.0,
          "exit_pnl_pct": -10.33,
          "exit_pnl_usd": -2.07,
          "exit_reason": "SL",
          "exit_time": "2026-02-18T10:01:43.869746+09:00",
          "highest_pnl": 0.0,
          "trail_activated": false
        },
        "current": {
          "act": 5.0,
          "trail": 3.0,
          "sl": -10.0,
          "exit_pnl_pct": -10.33,
          "exit_pnl_usd": -2.07,
          "exit_reason": "SL",
          "exit_time": "2026-02-18T10:01:43.869746+09:00",
          "highest_pnl": 0.0,
          "trail_activated": false
        },
        "moderate": {
          "act": 3.0,
          "trail": 2.0,
          "sl": -10.0,
          "exit_pnl_pct": -10.33,
          "exit_pnl_usd": -2.07,
          "exit_reason": "SL",
          "exit_time": "2026-02-18T10:01:43.869746+09:00",
          "highest_pnl": 0.0,
          "trail_activated": false
        },
        "tight": {
          "act": 3.0,
          "trail": 1.5,
          "sl": -10.0,
          "exit_pnl_pct": -10.33,
          "exit_pnl_usd": -2.07,
          "exit_reason": "SL",
          "exit_time": "2026-02-18T10:01:43.869746+09:00",
          "highest_pnl": 0.0,
          "trail_activated": false
        },
        "aggressive": {
          "act": 2.0,
          "trail": 1.0,
          "sl": -10.0,
          "exit_pnl_pct": -10.33,
          "exit_pnl_usd": -2.07,
          "exit_reason": "SL",
          "exit_time": "2026-02-18T10:01:43.869746+09:00",
          "highest_pnl": 0.0,
          "trail_activated": false
        },
        "wide_trail": {
          "act": 5.0,
          "trail": 2.0,
          "sl": -15.0,
          "exit_pnl_pct": -10.74,
          "exit_pnl_usd": -2.15,
          "exit_reason": "TIMEOUT",
          "exit_time": "2026-02-18T10:29:08.860390+09:00",
          "highest_pnl": 0.0,
          "trail_activated": false
        },
        "wide_sl15": {
          "act": 5.0,
          "trail": 3.0,
          "sl": -15.0,
          "exit_pnl_pct": -10.74,
          "exit_pnl_usd": -2.15,
          "exit_reason": "TIMEOUT",
          "exit_time": "2026-02-18T10:29:08.860390+09:00",
          "highest_pnl": 0.0,
          "trail_activated": false
        }
      },
      "momentum_exit": {
        "param_used": "conservative",
        "buys_1h": 9,
        "exit_pnl_pct": -10.33,
        "exit_pnl_usd": -2.07,
        "exit_reason": "SL"
      },
      "filter_match": {
        "live": true
      }
    },
    {
      "address": "8X9FraAEXey69hM1Nh6S173bFxCweyDnjHgVU6UMpump",
      "symbol": "LEGOINU",
      "entry_time": "2026-02-18T08:30:05.906052+09:00",
      "entry_price": 0.00020776749999999999,
      "amount_usd": 20.0,
      "score": 45.55073858151431,
      "grade": "C",
      "liquidity": 35446.21,
      "volume_24h": 57267.64,
      "token_age_min": 7514.6,
      "peak_pnl_pct": 0.0,
      "price_points": 499,
      "pc_5m": 17.35,
      "pc_1h": 13.69,
      "buys_1h": 13,
      "sells_1h": 12,
      "bs_ratio": 0.0,
      "completed_at": "2026-02-18T10:30:34.952429+09:00",
      "results": {
        "live": {
          "act": 5.0,
          "trail": 2.0,
          "sl": -10.0,
          "exit_pnl_pct": -10.23,
          "exit_pnl_usd": -2.05,
          "exit_reason": "SL",
          "exit_time": "2026-02-18T10:29:19.992386+09:00",
          "highest_pnl": 0.0,
          "trail_activated": false
        },
        "conservative": {
          "act": 8.0,
          "trail": 3.0,
          "sl": -10.0,
          "exit_pnl_pct": -10.23,
          "exit_pnl_usd": -2.05,
          "exit_reason": "SL",
          "exit_time": "2026-02-18T10:29:19.992386+09:00",
          "highest_pnl": 0.0,
          "trail_activated": false
        },
        "current": {
          "act": 5.0,
          "trail": 3.0,
          "sl": -10.0,
          "exit_pnl_pct": -10.23,
          "exit_pnl_usd": -2.05,
          "exit_reason": "SL",
          "exit_time": "2026-02-18T10:29:19.992386+09:00",
          "highest_pnl": 0.0,
          "trail_activated": false
        },
        "moderate": {
          "act": 3.0,
          "trail": 2.0,
          "sl": -10.0,
          "exit_pnl_pct": -10.23,
          "exit_pnl_usd": -2.05,
          "exit_reason": "SL",
          "exit_time": "2026-02-18T10:29:19.992386+09:00",
          "highest_pnl": 0.0,
          "trail_activated": false
        },
        "tight": {
          "act": 3.0,
          "trail": 1.5,
          "sl": -10.0,
          "exit_pnl_pct": -10.23,
          "exit_pnl_usd": -2.05,
          "exit_reason": "SL",
          "exit_time": "2026-02-18T10:29:19.992386+09:00",
          "highest_pnl": 0.0,
          "trail_activated": false
        },
        "aggressive": {
          "act": 2.0,
          "trail": 1.0,
          "sl": -10.0,
          "exit_pnl_pct": -10.23,
          "exit_pnl_usd": -2.05,
          "exit_reason": "SL",
          "exit_time": "2026-02-18T10:29:19.992386+09:00",
          "highest_pnl": 0.0,
          "trail_activated": false
        },
        "wide_trail": {
          "act": 5.0,
          "trail": 2.0,
          "sl": -15.0,
          "exit_pnl_pct": -10.23,
          "exit_pnl_usd": -2.05,
          "exit_reason": "TIMEOUT",
          "exit_time": "2026-02-18T10:30:34.949849+09:00",
          "highest_pnl": 0.0,
          "trail_activated": false
        },
        "wide_sl15": {
          "act": 5.0,
          "trail": 3.0,
          "sl": -15.0,
          "exit_pnl_pct": -10.23,
          "exit_pnl_usd": -2.05,
          "exit_reason": "TIMEOUT",
          "exit_time": "2026-02-18T10:30:34.949849+09:00",
          "highest_pnl": 0.0,
          "trail_activated": false
        }
      },
      "momentum_exit": {
        "param_used": "conservative",
        "buys_1h": 13,
        "exit_pnl_pct": -10.23,
        "exit_pnl_usd": -2.05,
        "exit_reason": "SL"
      },
      "filter_match": {
        "live": true
      }
    }
  ]
}