{
  "timestamp": "2026-02-17T04:28:31.023991",
  "wallet_address": "CdJSUeHX49eFK8hixbfDKNRLTakYcy59MbVEh8pDnn9U",
  "sol_balance": 1.176646792,
  "usdc_balance": 270.367301,
  "wbtc_balance": 0,
  "bnb_balance": 0.04898556,
  "sol_price_usd": 84.56,
  "btc_price_usd": 67965,
  "bnb_price_usd": 616.13,
  "eth_price_usd": 1972.01,
  "sol_value_usd": 99.49725273152,
  "wbtc_value_usd": 0,
  "bnb_value_usd": 30.181473082799997,
  "total_usd": 402.11,
  "meme_holdings": {
    "BRICKS": {
      "amount": 1e-06,
      "price": 1.4e-05,
      "value": 1.3999999999999999e-11,
      "mint": "Eqipr2xFuZccQErcCeJEoYGKTPkAdb7CHwJNZWPcpump"
    },
    "NeeDoh": {
      "amount": 32124.812128,
      "price": 6.417e-05,
      "value": 2.0614491942537603,
      "mint": "4fCwRhFEEMeqnervnjCCzQyw436g5WJKPKk7QPC6pump"
    }
  }
}